{"name":"暗界神使","targetUrl":"https://www.booktxt.net/1_10184","author":"火红森林","downloadUrl":"/modules/article/txtarticle.php?id=10184","allChapterNumber":243,"chapterList":["https://www.booktxt.net/1_10184/4432174.html","https://www.booktxt.net/1_10184/4432175.html","https://www.booktxt.net/1_10184/4432176.html","https://www.booktxt.net/1_10184/4432177.html","https://www.booktxt.net/1_10184/4432178.html","https://www.booktxt.net/1_10184/4432179.html","https://www.booktxt.net/1_10184/4432180.html","https://www.booktxt.net/1_10184/4432181.html","https://www.booktxt.net/1_10184/4432182.html","https://www.booktxt.net/1_10184/4432183.html","https://www.booktxt.net/1_10184/4432184.html","https://www.booktxt.net/1_10184/4432185.html","https://www.booktxt.net/1_10184/4432186.html","https://www.booktxt.net/1_10184/4432187.html","https://www.booktxt.net/1_10184/4432188.html","https://www.booktxt.net/1_10184/4432189.html","https://www.booktxt.net/1_10184/4432190.html","https://www.booktxt.net/1_10184/4432191.html","https://www.booktxt.net/1_10184/4432192.html","https://www.booktxt.net/1_10184/4432193.html","https://www.booktxt.net/1_10184/4432194.html","https://www.booktxt.net/1_10184/4432195.html","https://www.booktxt.net/1_10184/4432196.html","https://www.booktxt.net/1_10184/4432197.html","https://www.booktxt.net/1_10184/4432198.html","https://www.booktxt.net/1_10184/4432199.html","https://www.booktxt.net/1_10184/4432200.html","https://www.booktxt.net/1_10184/4432201.html","https://www.booktxt.net/1_10184/4432202.html","https://www.booktxt.net/1_10184/4432203.html","https://www.booktxt.net/1_10184/4432204.html","https://www.booktxt.net/1_10184/4432205.html","https://www.booktxt.net/1_10184/4432206.html","https://www.booktxt.net/1_10184/4432207.html","https://www.booktxt.net/1_10184/4432208.html","https://www.booktxt.net/1_10184/4432209.html","https://www.booktxt.net/1_10184/4432210.html","https://www.booktxt.net/1_10184/4432211.html","https://www.booktxt.net/1_10184/4432212.html","https://www.booktxt.net/1_10184/4432213.html","https://www.booktxt.net/1_10184/4432214.html","https://www.booktxt.net/1_10184/4432215.html","https://www.booktxt.net/1_10184/4432216.html","https://www.booktxt.net/1_10184/4432217.html","https://www.booktxt.net/1_10184/4432218.html","https://www.booktxt.net/1_10184/4432219.html","https://www.booktxt.net/1_10184/4432220.html","https://www.booktxt.net/1_10184/4432221.html","https://www.booktxt.net/1_10184/4432222.html","https://www.booktxt.net/1_10184/4432224.html","https://www.booktxt.net/1_10184/4432225.html","https://www.booktxt.net/1_10184/4432226.html","https://www.booktxt.net/1_10184/4432227.html","https://www.booktxt.net/1_10184/4432228.html","https://www.booktxt.net/1_10184/4432229.html","https://www.booktxt.net/1_10184/4432230.html","https://www.booktxt.net/1_10184/4432231.html","https://www.booktxt.net/1_10184/4432232.html","https://www.booktxt.net/1_10184/4432233.html","https://www.booktxt.net/1_10184/4432234.html","https://www.booktxt.net/1_10184/4432235.html","https://www.booktxt.net/1_10184/4432236.html","https://www.booktxt.net/1_10184/4432237.html","https://www.booktxt.net/1_10184/4432238.html","https://www.booktxt.net/1_10184/4432239.html","https://www.booktxt.net/1_10184/4432240.html","https://www.booktxt.net/1_10184/4432241.html","https://www.booktxt.net/1_10184/4432242.html","https://www.booktxt.net/1_10184/4432243.html","https://www.booktxt.net/1_10184/4432244.html","https://www.booktxt.net/1_10184/4432245.html","https://www.booktxt.net/1_10184/4432246.html","https://www.booktxt.net/1_10184/4432247.html","https://www.booktxt.net/1_10184/4432248.html","https://www.booktxt.net/1_10184/4432249.html","https://www.booktxt.net/1_10184/4432250.html","https://www.booktxt.net/1_10184/4432251.html","https://www.booktxt.net/1_10184/4432252.html","https://www.booktxt.net/1_10184/4432253.html","https://www.booktxt.net/1_10184/4432254.html","https://www.booktxt.net/1_10184/4432255.html","https://www.booktxt.net/1_10184/4432256.html","https://www.booktxt.net/1_10184/4432257.html","https://www.booktxt.net/1_10184/4432258.html","https://www.booktxt.net/1_10184/4432259.html","https://www.booktxt.net/1_10184/4432260.html","https://www.booktxt.net/1_10184/4432261.html","https://www.booktxt.net/1_10184/4432262.html","https://www.booktxt.net/1_10184/4432263.html","https://www.booktxt.net/1_10184/4432264.html","https://www.booktxt.net/1_10184/4432265.html","https://www.booktxt.net/1_10184/4432266.html","https://www.booktxt.net/1_10184/4432267.html","https://www.booktxt.net/1_10184/4432268.html","https://www.booktxt.net/1_10184/4432269.html","https://www.booktxt.net/1_10184/4432270.html","https://www.booktxt.net/1_10184/4432271.html","https://www.booktxt.net/1_10184/4432272.html","https://www.booktxt.net/1_10184/4432273.html","https://www.booktxt.net/1_10184/4432274.html","https://www.booktxt.net/1_10184/4432275.html","https://www.booktxt.net/1_10184/4432276.html","https://www.booktxt.net/1_10184/4432277.html","https://www.booktxt.net/1_10184/4432278.html","https://www.booktxt.net/1_10184/4432279.html","https://www.booktxt.net/1_10184/4432280.html","https://www.booktxt.net/1_10184/4432281.html","https://www.booktxt.net/1_10184/4432282.html","https://www.booktxt.net/1_10184/4432283.html","https://www.booktxt.net/1_10184/4432284.html","https://www.booktxt.net/1_10184/4432285.html","https://www.booktxt.net/1_10184/4432286.html","https://www.booktxt.net/1_10184/4432287.html","https://www.booktxt.net/1_10184/4432288.html","https://www.booktxt.net/1_10184/4432289.html","https://www.booktxt.net/1_10184/4432290.html","https://www.booktxt.net/1_10184/4432291.html","https://www.booktxt.net/1_10184/4432292.html","https://www.booktxt.net/1_10184/4432293.html","https://www.booktxt.net/1_10184/4432294.html","https://www.booktxt.net/1_10184/4432295.html","https://www.booktxt.net/1_10184/4432296.html","https://www.booktxt.net/1_10184/4432297.html","https://www.booktxt.net/1_10184/4432298.html","https://www.booktxt.net/1_10184/4432299.html","https://www.booktxt.net/1_10184/4432300.html","https://www.booktxt.net/1_10184/4432301.html","https://www.booktxt.net/1_10184/4432302.html","https://www.booktxt.net/1_10184/4432303.html","https://www.booktxt.net/1_10184/4432304.html","https://www.booktxt.net/1_10184/4432305.html","https://www.booktxt.net/1_10184/4432306.html","https://www.booktxt.net/1_10184/4432307.html","https://www.booktxt.net/1_10184/4432308.html","https://www.booktxt.net/1_10184/4432309.html","https://www.booktxt.net/1_10184/4432310.html","https://www.booktxt.net/1_10184/4432311.html","https://www.booktxt.net/1_10184/4432312.html","https://www.booktxt.net/1_10184/4432313.html","https://www.booktxt.net/1_10184/4432314.html","https://www.booktxt.net/1_10184/4432315.html","https://www.booktxt.net/1_10184/4432316.html","https://www.booktxt.net/1_10184/4432317.html","https://www.booktxt.net/1_10184/4432318.html","https://www.booktxt.net/1_10184/4432319.html","https://www.booktxt.net/1_10184/4432320.html","https://www.booktxt.net/1_10184/4432321.html","https://www.booktxt.net/1_10184/4432322.html","https://www.booktxt.net/1_10184/4432323.html","https://www.booktxt.net/1_10184/4432324.html","https://www.booktxt.net/1_10184/4432325.html","https://www.booktxt.net/1_10184/4432327.html","https://www.booktxt.net/1_10184/4432328.html","https://www.booktxt.net/1_10184/4432329.html","https://www.booktxt.net/1_10184/4432330.html","https://www.booktxt.net/1_10184/4432331.html","https://www.booktxt.net/1_10184/4432332.html","https://www.booktxt.net/1_10184/4432333.html","https://www.booktxt.net/1_10184/4432334.html","https://www.booktxt.net/1_10184/4432335.html","https://www.booktxt.net/1_10184/4432336.html","https://www.booktxt.net/1_10184/4432337.html","https://www.booktxt.net/1_10184/4432338.html","https://www.booktxt.net/1_10184/4432339.html","https://www.booktxt.net/1_10184/4432340.html","https://www.booktxt.net/1_10184/4432341.html","https://www.booktxt.net/1_10184/4432342.html","https://www.booktxt.net/1_10184/4432343.html","https://www.booktxt.net/1_10184/4432344.html","https://www.booktxt.net/1_10184/4432345.html","https://www.booktxt.net/1_10184/4432346.html","https://www.booktxt.net/1_10184/4432347.html","https://www.booktxt.net/1_10184/4432348.html","https://www.booktxt.net/1_10184/4432349.html","https://www.booktxt.net/1_10184/4432350.html","https://www.booktxt.net/1_10184/4432351.html","https://www.booktxt.net/1_10184/4432352.html","https://www.booktxt.net/1_10184/4432353.html","https://www.booktxt.net/1_10184/4432354.html","https://www.booktxt.net/1_10184/4432355.html","https://www.booktxt.net/1_10184/4432356.html","https://www.booktxt.net/1_10184/4432357.html","https://www.booktxt.net/1_10184/4432358.html","https://www.booktxt.net/1_10184/4465218.html","https://www.booktxt.net/1_10184/4482066.html","https://www.booktxt.net/1_10184/4508595.html","https://www.booktxt.net/1_10184/4536059.html","https://www.booktxt.net/1_10184/4560665.html","https://www.booktxt.net/1_10184/4566801.html","https://www.booktxt.net/1_10184/4575987.html","https://www.booktxt.net/1_10184/4582278.html","https://www.booktxt.net/1_10184/4590182.html","https://www.booktxt.net/1_10184/4596167.html","https://www.booktxt.net/1_10184/4603121.html","https://www.booktxt.net/1_10184/4609069.html","https://www.booktxt.net/1_10184/4615352.html","https://www.booktxt.net/1_10184/4622201.html","https://www.booktxt.net/1_10184/4650904.html","https://www.booktxt.net/1_10184/4650905.html","https://www.booktxt.net/1_10184/4650906.html","https://www.booktxt.net/1_10184/4663875.html","https://www.booktxt.net/1_10184/4670797.html","https://www.booktxt.net/1_10184/4743696.html","https://www.booktxt.net/1_10184/4743697.html","https://www.booktxt.net/1_10184/4743698.html","https://www.booktxt.net/1_10184/4743699.html","https://www.booktxt.net/1_10184/4743700.html","https://www.booktxt.net/1_10184/4744402.html","https://www.booktxt.net/1_10184/4760216.html","https://www.booktxt.net/1_10184/4790338.html","https://www.booktxt.net/1_10184/4799211.html","https://www.booktxt.net/1_10184/4810119.html","https://www.booktxt.net/1_10184/4827719.html","https://www.booktxt.net/1_10184/4842591.html","https://www.booktxt.net/1_10184/4852697.html","https://www.booktxt.net/1_10184/4862540.html","https://www.booktxt.net/1_10184/4873431.html","https://www.booktxt.net/1_10184/4880243.html","https://www.booktxt.net/1_10184/4893718.html","https://www.booktxt.net/1_10184/4900897.html","https://www.booktxt.net/1_10184/4908937.html","https://www.booktxt.net/1_10184/4931903.html","https://www.booktxt.net/1_10184/4931904.html","https://www.booktxt.net/1_10184/4941637.html","https://www.booktxt.net/1_10184/4953690.html","https://www.booktxt.net/1_10184/4953691.html","https://www.booktxt.net/1_10184/4971791.html","https://www.booktxt.net/1_10184/4980229.html","https://www.booktxt.net/1_10184/4989850.html","https://www.booktxt.net/1_10184/4999143.html","https://www.booktxt.net/1_10184/5008345.html","https://www.booktxt.net/1_10184/5015730.html","https://www.booktxt.net/1_10184/5022376.html","https://www.booktxt.net/1_10184/5097232.html","https://www.booktxt.net/1_10184/5106764.html","https://www.booktxt.net/1_10184/5117387.html","https://www.booktxt.net/1_10184/5144401.html","https://www.booktxt.net/1_10184/5237200.html","https://www.booktxt.net/1_10184/5237201.html","https://www.booktxt.net/1_10184/5241891.html","https://www.booktxt.net/1_10184/5249406.html","https://www.booktxt.net/1_10184/5256354.html","https://www.booktxt.net/1_10184/5263132.html"],"graspTimeDifference":1860,"lastUpdateTime":"02-22","index":10184,"timeStamp":1556112021929}