{"name":"都市最强修真学生","targetUrl":"https://www.booktxt.net/1_10274","author":"林北留","downloadUrl":"/modules/article/txtarticle.php?id=10274","allChapterNumber":2057,"chapterList":["https://www.booktxt.net/1_10274/4484911.html","https://www.booktxt.net/1_10274/4484912.html","https://www.booktxt.net/1_10274/4484915.html","https://www.booktxt.net/1_10274/4484917.html","https://www.booktxt.net/1_10274/4484920.html","https://www.booktxt.net/1_10274/4484922.html","https://www.booktxt.net/1_10274/4484924.html","https://www.booktxt.net/1_10274/4484926.html","https://www.booktxt.net/1_10274/4484929.html","https://www.booktxt.net/1_10274/4484931.html","https://www.booktxt.net/1_10274/4484933.html","https://www.booktxt.net/1_10274/4484935.html","https://www.booktxt.net/1_10274/4484938.html","https://www.booktxt.net/1_10274/4484940.html","https://www.booktxt.net/1_10274/4484942.html","https://www.booktxt.net/1_10274/4484944.html","https://www.booktxt.net/1_10274/4484946.html","https://www.booktxt.net/1_10274/4484949.html","https://www.booktxt.net/1_10274/4484951.html","https://www.booktxt.net/1_10274/4484954.html","https://www.booktxt.net/1_10274/4484955.html","https://www.booktxt.net/1_10274/4484958.html","https://www.booktxt.net/1_10274/4484960.html","https://www.booktxt.net/1_10274/4484964.html","https://www.booktxt.net/1_10274/4484965.html","https://www.booktxt.net/1_10274/4484968.html","https://www.booktxt.net/1_10274/4484970.html","https://www.booktxt.net/1_10274/4484973.html","https://www.booktxt.net/1_10274/4484974.html","https://www.booktxt.net/1_10274/4484977.html","https://www.booktxt.net/1_10274/4484979.html","https://www.booktxt.net/1_10274/4484982.html","https://www.booktxt.net/1_10274/4484983.html","https://www.booktxt.net/1_10274/4484986.html","https://www.booktxt.net/1_10274/4484988.html","https://www.booktxt.net/1_10274/4484991.html","https://www.booktxt.net/1_10274/4484993.html","https://www.booktxt.net/1_10274/4484996.html","https://www.booktxt.net/1_10274/4484999.html","https://www.booktxt.net/1_10274/4485000.html","https://www.booktxt.net/1_10274/4485003.html","https://www.booktxt.net/1_10274/4485005.html","https://www.booktxt.net/1_10274/4485007.html","https://www.booktxt.net/1_10274/4485009.html","https://www.booktxt.net/1_10274/4485011.html","https://www.booktxt.net/1_10274/4485014.html","https://www.booktxt.net/1_10274/4485015.html","https://www.booktxt.net/1_10274/4485018.html","https://www.booktxt.net/1_10274/4485020.html","https://www.booktxt.net/1_10274/4485022.html","https://www.booktxt.net/1_10274/4485024.html","https://www.booktxt.net/1_10274/4485027.html","https://www.booktxt.net/1_10274/4485029.html","https://www.booktxt.net/1_10274/4485032.html","https://www.booktxt.net/1_10274/4485034.html","https://www.booktxt.net/1_10274/4485036.html","https://www.booktxt.net/1_10274/4485037.html","https://www.booktxt.net/1_10274/4485040.html","https://www.booktxt.net/1_10274/4485042.html","https://www.booktxt.net/1_10274/4485045.html","https://www.booktxt.net/1_10274/4485047.html","https://www.booktxt.net/1_10274/4485049.html","https://www.booktxt.net/1_10274/4485051.html","https://www.booktxt.net/1_10274/4485053.html","https://www.booktxt.net/1_10274/4485056.html","https://www.booktxt.net/1_10274/4485059.html","https://www.booktxt.net/1_10274/4485060.html","https://www.booktxt.net/1_10274/4485063.html","https://www.booktxt.net/1_10274/4485065.html","https://www.booktxt.net/1_10274/4485068.html","https://www.booktxt.net/1_10274/4485070.html","https://www.booktxt.net/1_10274/4485073.html","https://www.booktxt.net/1_10274/4485076.html","https://www.booktxt.net/1_10274/4485078.html","https://www.booktxt.net/1_10274/4485081.html","https://www.booktxt.net/1_10274/4485083.html","https://www.booktxt.net/1_10274/4485086.html","https://www.booktxt.net/1_10274/4485087.html","https://www.booktxt.net/1_10274/4485090.html","https://www.booktxt.net/1_10274/4485093.html","https://www.booktxt.net/1_10274/4485095.html","https://www.booktxt.net/1_10274/4485098.html","https://www.booktxt.net/1_10274/4485101.html","https://www.booktxt.net/1_10274/4485103.html","https://www.booktxt.net/1_10274/4485106.html","https://www.booktxt.net/1_10274/4485109.html","https://www.booktxt.net/1_10274/4485111.html","https://www.booktxt.net/1_10274/4485113.html","https://www.booktxt.net/1_10274/4485115.html","https://www.booktxt.net/1_10274/4485118.html","https://www.booktxt.net/1_10274/4485120.html","https://www.booktxt.net/1_10274/4485123.html","https://www.booktxt.net/1_10274/4485125.html","https://www.booktxt.net/1_10274/4485127.html","https://www.booktxt.net/1_10274/4485129.html","https://www.booktxt.net/1_10274/4485132.html","https://www.booktxt.net/1_10274/4485135.html","https://www.booktxt.net/1_10274/4485136.html","https://www.booktxt.net/1_10274/4485139.html","https://www.booktxt.net/1_10274/4485141.html","https://www.booktxt.net/1_10274/4485144.html","https://www.booktxt.net/1_10274/4485146.html","https://www.booktxt.net/1_10274/4485148.html","https://www.booktxt.net/1_10274/4485150.html","https://www.booktxt.net/1_10274/4485153.html","https://www.booktxt.net/1_10274/4485154.html","https://www.booktxt.net/1_10274/4485157.html","https://www.booktxt.net/1_10274/4485160.html","https://www.booktxt.net/1_10274/4485162.html","https://www.booktxt.net/1_10274/4485165.html","https://www.booktxt.net/1_10274/4485169.html","https://www.booktxt.net/1_10274/4485170.html","https://www.booktxt.net/1_10274/4485173.html","https://www.booktxt.net/1_10274/4485175.html","https://www.booktxt.net/1_10274/4485178.html","https://www.booktxt.net/1_10274/4485180.html","https://www.booktxt.net/1_10274/4485183.html","https://www.booktxt.net/1_10274/4485184.html","https://www.booktxt.net/1_10274/4485187.html","https://www.booktxt.net/1_10274/4485190.html","https://www.booktxt.net/1_10274/4485192.html","https://www.booktxt.net/1_10274/4485195.html","https://www.booktxt.net/1_10274/4485196.html","https://www.booktxt.net/1_10274/4485199.html","https://www.booktxt.net/1_10274/4485202.html","https://www.booktxt.net/1_10274/4485204.html","https://www.booktxt.net/1_10274/4485207.html","https://www.booktxt.net/1_10274/4485208.html","https://www.booktxt.net/1_10274/4485211.html","https://www.booktxt.net/1_10274/4485214.html","https://www.booktxt.net/1_10274/4485215.html","https://www.booktxt.net/1_10274/4485218.html","https://www.booktxt.net/1_10274/4485220.html","https://www.booktxt.net/1_10274/4485223.html","https://www.booktxt.net/1_10274/4485225.html","https://www.booktxt.net/1_10274/4485228.html","https://www.booktxt.net/1_10274/4485231.html","https://www.booktxt.net/1_10274/4485232.html","https://www.booktxt.net/1_10274/4485235.html","https://www.booktxt.net/1_10274/4485238.html","https://www.booktxt.net/1_10274/4485240.html","https://www.booktxt.net/1_10274/4485243.html","https://www.booktxt.net/1_10274/4485244.html","https://www.booktxt.net/1_10274/4485247.html","https://www.booktxt.net/1_10274/4485249.html","https://www.booktxt.net/1_10274/4485252.html","https://www.booktxt.net/1_10274/4485254.html","https://www.booktxt.net/1_10274/4485257.html","https://www.booktxt.net/1_10274/4485260.html","https://www.booktxt.net/1_10274/4485262.html","https://www.booktxt.net/1_10274/4485265.html","https://www.booktxt.net/1_10274/4485267.html","https://www.booktxt.net/1_10274/4485270.html","https://www.booktxt.net/1_10274/4485272.html","https://www.booktxt.net/1_10274/4485274.html","https://www.booktxt.net/1_10274/4485277.html","https://www.booktxt.net/1_10274/4485279.html","https://www.booktxt.net/1_10274/4485282.html","https://www.booktxt.net/1_10274/4485284.html","https://www.booktxt.net/1_10274/4485286.html","https://www.booktxt.net/1_10274/4485289.html","https://www.booktxt.net/1_10274/4485291.html","https://www.booktxt.net/1_10274/4485293.html","https://www.booktxt.net/1_10274/4485294.html","https://www.booktxt.net/1_10274/4485295.html","https://www.booktxt.net/1_10274/4485297.html","https://www.booktxt.net/1_10274/4485299.html","https://www.booktxt.net/1_10274/4485302.html","https://www.booktxt.net/1_10274/4485303.html","https://www.booktxt.net/1_10274/4485306.html","https://www.booktxt.net/1_10274/4485309.html","https://www.booktxt.net/1_10274/4485311.html","https://www.booktxt.net/1_10274/4485314.html","https://www.booktxt.net/1_10274/4485316.html","https://www.booktxt.net/1_10274/4485319.html","https://www.booktxt.net/1_10274/4485320.html","https://www.booktxt.net/1_10274/4485323.html","https://www.booktxt.net/1_10274/4485325.html","https://www.booktxt.net/1_10274/4485328.html","https://www.booktxt.net/1_10274/4485330.html","https://www.booktxt.net/1_10274/4485333.html","https://www.booktxt.net/1_10274/4485335.html","https://www.booktxt.net/1_10274/4485338.html","https://www.booktxt.net/1_10274/4485341.html","https://www.booktxt.net/1_10274/4485342.html","https://www.booktxt.net/1_10274/4485345.html","https://www.booktxt.net/1_10274/4485347.html","https://www.booktxt.net/1_10274/4485350.html","https://www.booktxt.net/1_10274/4485351.html","https://www.booktxt.net/1_10274/4485354.html","https://www.booktxt.net/1_10274/4485355.html","https://www.booktxt.net/1_10274/4485358.html","https://www.booktxt.net/1_10274/4485360.html","https://www.booktxt.net/1_10274/4485363.html","https://www.booktxt.net/1_10274/4485366.html","https://www.booktxt.net/1_10274/4485368.html","https://www.booktxt.net/1_10274/4485370.html","https://www.booktxt.net/1_10274/4485372.html","https://www.booktxt.net/1_10274/4485375.html","https://www.booktxt.net/1_10274/4485378.html","https://www.booktxt.net/1_10274/4485379.html","https://www.booktxt.net/1_10274/4485382.html","https://www.booktxt.net/1_10274/4485384.html","https://www.booktxt.net/1_10274/4485387.html","https://www.booktxt.net/1_10274/4485390.html","https://www.booktxt.net/1_10274/4485393.html","https://www.booktxt.net/1_10274/4485395.html","https://www.booktxt.net/1_10274/4485397.html","https://www.booktxt.net/1_10274/4485399.html","https://www.booktxt.net/1_10274/4485402.html","https://www.booktxt.net/1_10274/4485405.html","https://www.booktxt.net/1_10274/4485408.html","https://www.booktxt.net/1_10274/4485410.html","https://www.booktxt.net/1_10274/4485413.html","https://www.booktxt.net/1_10274/4485416.html","https://www.booktxt.net/1_10274/4485417.html","https://www.booktxt.net/1_10274/4485420.html","https://www.booktxt.net/1_10274/4485423.html","https://www.booktxt.net/1_10274/4485425.html","https://www.booktxt.net/1_10274/4485427.html","https://www.booktxt.net/1_10274/4485428.html","https://www.booktxt.net/1_10274/4485429.html","https://www.booktxt.net/1_10274/4485430.html","https://www.booktxt.net/1_10274/4485431.html","https://www.booktxt.net/1_10274/4485433.html","https://www.booktxt.net/1_10274/4485434.html","https://www.booktxt.net/1_10274/4485435.html","https://www.booktxt.net/1_10274/4485437.html","https://www.booktxt.net/1_10274/4485439.html","https://www.booktxt.net/1_10274/4485441.html","https://www.booktxt.net/1_10274/4485443.html","https://www.booktxt.net/1_10274/4485445.html","https://www.booktxt.net/1_10274/4485447.html","https://www.booktxt.net/1_10274/4485450.html","https://www.booktxt.net/1_10274/4485452.html","https://www.booktxt.net/1_10274/4485454.html","https://www.booktxt.net/1_10274/4485456.html","https://www.booktxt.net/1_10274/4485458.html","https://www.booktxt.net/1_10274/4485460.html","https://www.booktxt.net/1_10274/4485462.html","https://www.booktxt.net/1_10274/4485463.html","https://www.booktxt.net/1_10274/4485465.html","https://www.booktxt.net/1_10274/4485467.html","https://www.booktxt.net/1_10274/4485469.html","https://www.booktxt.net/1_10274/4485472.html","https://www.booktxt.net/1_10274/4485474.html","https://www.booktxt.net/1_10274/4485476.html","https://www.booktxt.net/1_10274/4485478.html","https://www.booktxt.net/1_10274/4485479.html","https://www.booktxt.net/1_10274/4485481.html","https://www.booktxt.net/1_10274/4485483.html","https://www.booktxt.net/1_10274/4485485.html","https://www.booktxt.net/1_10274/4485487.html","https://www.booktxt.net/1_10274/4485489.html","https://www.booktxt.net/1_10274/4485490.html","https://www.booktxt.net/1_10274/4485492.html","https://www.booktxt.net/1_10274/4485494.html","https://www.booktxt.net/1_10274/4485496.html","https://www.booktxt.net/1_10274/4485498.html","https://www.booktxt.net/1_10274/4485500.html","https://www.booktxt.net/1_10274/4485502.html","https://www.booktxt.net/1_10274/4485504.html","https://www.booktxt.net/1_10274/4485506.html","https://www.booktxt.net/1_10274/4485508.html","https://www.booktxt.net/1_10274/4485510.html","https://www.booktxt.net/1_10274/4485512.html","https://www.booktxt.net/1_10274/4485514.html","https://www.booktxt.net/1_10274/4485516.html","https://www.booktxt.net/1_10274/4485518.html","https://www.booktxt.net/1_10274/4485520.html","https://www.booktxt.net/1_10274/4485522.html","https://www.booktxt.net/1_10274/4485524.html","https://www.booktxt.net/1_10274/4485525.html","https://www.booktxt.net/1_10274/4485527.html","https://www.booktxt.net/1_10274/4485529.html","https://www.booktxt.net/1_10274/4485531.html","https://www.booktxt.net/1_10274/4485533.html","https://www.booktxt.net/1_10274/4485534.html","https://www.booktxt.net/1_10274/4485536.html","https://www.booktxt.net/1_10274/4485538.html","https://www.booktxt.net/1_10274/4485540.html","https://www.booktxt.net/1_10274/4485542.html","https://www.booktxt.net/1_10274/4485544.html","https://www.booktxt.net/1_10274/4485546.html","https://www.booktxt.net/1_10274/4485548.html","https://www.booktxt.net/1_10274/4485550.html","https://www.booktxt.net/1_10274/4485552.html","https://www.booktxt.net/1_10274/4485554.html","https://www.booktxt.net/1_10274/4485556.html","https://www.booktxt.net/1_10274/4485558.html","https://www.booktxt.net/1_10274/4485560.html","https://www.booktxt.net/1_10274/4485562.html","https://www.booktxt.net/1_10274/4485564.html","https://www.booktxt.net/1_10274/4485566.html","https://www.booktxt.net/1_10274/4485567.html","https://www.booktxt.net/1_10274/4485569.html","https://www.booktxt.net/1_10274/4485571.html","https://www.booktxt.net/1_10274/4485573.html","https://www.booktxt.net/1_10274/4485575.html","https://www.booktxt.net/1_10274/4485577.html","https://www.booktxt.net/1_10274/4485579.html","https://www.booktxt.net/1_10274/4485580.html","https://www.booktxt.net/1_10274/4485582.html","https://www.booktxt.net/1_10274/4485584.html","https://www.booktxt.net/1_10274/4485586.html","https://www.booktxt.net/1_10274/4485588.html","https://www.booktxt.net/1_10274/4485590.html","https://www.booktxt.net/1_10274/4485592.html","https://www.booktxt.net/1_10274/4485594.html","https://www.booktxt.net/1_10274/4485596.html","https://www.booktxt.net/1_10274/4485598.html","https://www.booktxt.net/1_10274/4485600.html","https://www.booktxt.net/1_10274/4485601.html","https://www.booktxt.net/1_10274/4485603.html","https://www.booktxt.net/1_10274/4485605.html","https://www.booktxt.net/1_10274/4485607.html","https://www.booktxt.net/1_10274/4485609.html","https://www.booktxt.net/1_10274/4485611.html","https://www.booktxt.net/1_10274/4485613.html","https://www.booktxt.net/1_10274/4485615.html","https://www.booktxt.net/1_10274/4485618.html","https://www.booktxt.net/1_10274/4485621.html","https://www.booktxt.net/1_10274/4485625.html","https://www.booktxt.net/1_10274/4485628.html","https://www.booktxt.net/1_10274/4485632.html","https://www.booktxt.net/1_10274/4485635.html","https://www.booktxt.net/1_10274/4485637.html","https://www.booktxt.net/1_10274/4485641.html","https://www.booktxt.net/1_10274/4485644.html","https://www.booktxt.net/1_10274/4485647.html","https://www.booktxt.net/1_10274/4485649.html","https://www.booktxt.net/1_10274/4485652.html","https://www.booktxt.net/1_10274/4485655.html","https://www.booktxt.net/1_10274/4485659.html","https://www.booktxt.net/1_10274/4485662.html","https://www.booktxt.net/1_10274/4485664.html","https://www.booktxt.net/1_10274/4485668.html","https://www.booktxt.net/1_10274/4485671.html","https://www.booktxt.net/1_10274/4485674.html","https://www.booktxt.net/1_10274/4485678.html","https://www.booktxt.net/1_10274/4485681.html","https://www.booktxt.net/1_10274/4485684.html","https://www.booktxt.net/1_10274/4485688.html","https://www.booktxt.net/1_10274/4485690.html","https://www.booktxt.net/1_10274/4485693.html","https://www.booktxt.net/1_10274/4485696.html","https://www.booktxt.net/1_10274/4485700.html","https://www.booktxt.net/1_10274/4485703.html","https://www.booktxt.net/1_10274/4485706.html","https://www.booktxt.net/1_10274/4485709.html","https://www.booktxt.net/1_10274/4485712.html","https://www.booktxt.net/1_10274/4485715.html","https://www.booktxt.net/1_10274/4485719.html","https://www.booktxt.net/1_10274/4485722.html","https://www.booktxt.net/1_10274/4485725.html","https://www.booktxt.net/1_10274/4485728.html","https://www.booktxt.net/1_10274/4485731.html","https://www.booktxt.net/1_10274/4485735.html","https://www.booktxt.net/1_10274/4485738.html","https://www.booktxt.net/1_10274/4485741.html","https://www.booktxt.net/1_10274/4485743.html","https://www.booktxt.net/1_10274/4485747.html","https://www.booktxt.net/1_10274/4485750.html","https://www.booktxt.net/1_10274/4485753.html","https://www.booktxt.net/1_10274/4485757.html","https://www.booktxt.net/1_10274/4485760.html","https://www.booktxt.net/1_10274/4485763.html","https://www.booktxt.net/1_10274/4485767.html","https://www.booktxt.net/1_10274/4485769.html","https://www.booktxt.net/1_10274/4485772.html","https://www.booktxt.net/1_10274/4485776.html","https://www.booktxt.net/1_10274/4485779.html","https://www.booktxt.net/1_10274/4485782.html","https://www.booktxt.net/1_10274/4485786.html","https://www.booktxt.net/1_10274/4485789.html","https://www.booktxt.net/1_10274/4485793.html","https://www.booktxt.net/1_10274/4485796.html","https://www.booktxt.net/1_10274/4485799.html","https://www.booktxt.net/1_10274/4485803.html","https://www.booktxt.net/1_10274/4485805.html","https://www.booktxt.net/1_10274/4485809.html","https://www.booktxt.net/1_10274/4485812.html","https://www.booktxt.net/1_10274/4485815.html","https://www.booktxt.net/1_10274/4485819.html","https://www.booktxt.net/1_10274/4485822.html","https://www.booktxt.net/1_10274/4485824.html","https://www.booktxt.net/1_10274/4485827.html","https://www.booktxt.net/1_10274/4485830.html","https://www.booktxt.net/1_10274/4485833.html","https://www.booktxt.net/1_10274/4485837.html","https://www.booktxt.net/1_10274/4485840.html","https://www.booktxt.net/1_10274/4485843.html","https://www.booktxt.net/1_10274/4485845.html","https://www.booktxt.net/1_10274/4485848.html","https://www.booktxt.net/1_10274/4485852.html","https://www.booktxt.net/1_10274/4485855.html","https://www.booktxt.net/1_10274/4485858.html","https://www.booktxt.net/1_10274/4485861.html","https://www.booktxt.net/1_10274/4485865.html","https://www.booktxt.net/1_10274/4485868.html","https://www.booktxt.net/1_10274/4485871.html","https://www.booktxt.net/1_10274/4485874.html","https://www.booktxt.net/1_10274/4485875.html","https://www.booktxt.net/1_10274/4485877.html","https://www.booktxt.net/1_10274/4485879.html","https://www.booktxt.net/1_10274/4485881.html","https://www.booktxt.net/1_10274/4485883.html","https://www.booktxt.net/1_10274/4485884.html","https://www.booktxt.net/1_10274/4485886.html","https://www.booktxt.net/1_10274/4485888.html","https://www.booktxt.net/1_10274/4485890.html","https://www.booktxt.net/1_10274/4485892.html","https://www.booktxt.net/1_10274/4485894.html","https://www.booktxt.net/1_10274/4485896.html","https://www.booktxt.net/1_10274/4485898.html","https://www.booktxt.net/1_10274/4485899.html","https://www.booktxt.net/1_10274/4485901.html","https://www.booktxt.net/1_10274/4485903.html","https://www.booktxt.net/1_10274/4485905.html","https://www.booktxt.net/1_10274/4485907.html","https://www.booktxt.net/1_10274/4485909.html","https://www.booktxt.net/1_10274/4485911.html","https://www.booktxt.net/1_10274/4485913.html","https://www.booktxt.net/1_10274/4485915.html","https://www.booktxt.net/1_10274/4485917.html","https://www.booktxt.net/1_10274/4485918.html","https://www.booktxt.net/1_10274/4485920.html","https://www.booktxt.net/1_10274/4485922.html","https://www.booktxt.net/1_10274/4485924.html","https://www.booktxt.net/1_10274/4485926.html","https://www.booktxt.net/1_10274/4485927.html","https://www.booktxt.net/1_10274/4485929.html","https://www.booktxt.net/1_10274/4485931.html","https://www.booktxt.net/1_10274/4485932.html","https://www.booktxt.net/1_10274/4485934.html","https://www.booktxt.net/1_10274/4485936.html","https://www.booktxt.net/1_10274/4485937.html","https://www.booktxt.net/1_10274/4485939.html","https://www.booktxt.net/1_10274/4485940.html","https://www.booktxt.net/1_10274/4485942.html","https://www.booktxt.net/1_10274/4485944.html","https://www.booktxt.net/1_10274/4485946.html","https://www.booktxt.net/1_10274/4485948.html","https://www.booktxt.net/1_10274/4485950.html","https://www.booktxt.net/1_10274/4485953.html","https://www.booktxt.net/1_10274/4485954.html","https://www.booktxt.net/1_10274/4485956.html","https://www.booktxt.net/1_10274/4485958.html","https://www.booktxt.net/1_10274/4485960.html","https://www.booktxt.net/1_10274/4485962.html","https://www.booktxt.net/1_10274/4485964.html","https://www.booktxt.net/1_10274/4485966.html","https://www.booktxt.net/1_10274/4485968.html","https://www.booktxt.net/1_10274/4485970.html","https://www.booktxt.net/1_10274/4485972.html","https://www.booktxt.net/1_10274/4485975.html","https://www.booktxt.net/1_10274/4485977.html","https://www.booktxt.net/1_10274/4485978.html","https://www.booktxt.net/1_10274/4485980.html","https://www.booktxt.net/1_10274/4485982.html","https://www.booktxt.net/1_10274/4485984.html","https://www.booktxt.net/1_10274/4485986.html","https://www.booktxt.net/1_10274/4485988.html","https://www.booktxt.net/1_10274/4485990.html","https://www.booktxt.net/1_10274/4485992.html","https://www.booktxt.net/1_10274/4485993.html","https://www.booktxt.net/1_10274/4485995.html","https://www.booktxt.net/1_10274/4485997.html","https://www.booktxt.net/1_10274/4485999.html","https://www.booktxt.net/1_10274/4486001.html","https://www.booktxt.net/1_10274/4486003.html","https://www.booktxt.net/1_10274/4486005.html","https://www.booktxt.net/1_10274/4486007.html","https://www.booktxt.net/1_10274/4486009.html","https://www.booktxt.net/1_10274/4486010.html","https://www.booktxt.net/1_10274/4486012.html","https://www.booktxt.net/1_10274/4486014.html","https://www.booktxt.net/1_10274/4486016.html","https://www.booktxt.net/1_10274/4486017.html","https://www.booktxt.net/1_10274/4486019.html","https://www.booktxt.net/1_10274/4486021.html","https://www.booktxt.net/1_10274/4486023.html","https://www.booktxt.net/1_10274/4486025.html","https://www.booktxt.net/1_10274/4486027.html","https://www.booktxt.net/1_10274/4486029.html","https://www.booktxt.net/1_10274/4486031.html","https://www.booktxt.net/1_10274/4486032.html","https://www.booktxt.net/1_10274/4486034.html","https://www.booktxt.net/1_10274/4486036.html","https://www.booktxt.net/1_10274/4486038.html","https://www.booktxt.net/1_10274/4486039.html","https://www.booktxt.net/1_10274/4486041.html","https://www.booktxt.net/1_10274/4486043.html","https://www.booktxt.net/1_10274/4486045.html","https://www.booktxt.net/1_10274/4486046.html","https://www.booktxt.net/1_10274/4486048.html","https://www.booktxt.net/1_10274/4486050.html","https://www.booktxt.net/1_10274/4486052.html","https://www.booktxt.net/1_10274/4486054.html","https://www.booktxt.net/1_10274/4486056.html","https://www.booktxt.net/1_10274/4486058.html","https://www.booktxt.net/1_10274/4486059.html","https://www.booktxt.net/1_10274/4486061.html","https://www.booktxt.net/1_10274/4486064.html","https://www.booktxt.net/1_10274/4486066.html","https://www.booktxt.net/1_10274/4486067.html","https://www.booktxt.net/1_10274/4486069.html","https://www.booktxt.net/1_10274/4486071.html","https://www.booktxt.net/1_10274/4486073.html","https://www.booktxt.net/1_10274/4486075.html","https://www.booktxt.net/1_10274/4486077.html","https://www.booktxt.net/1_10274/4486079.html","https://www.booktxt.net/1_10274/4486081.html","https://www.booktxt.net/1_10274/4486083.html","https://www.booktxt.net/1_10274/4486085.html","https://www.booktxt.net/1_10274/4486087.html","https://www.booktxt.net/1_10274/4486088.html","https://www.booktxt.net/1_10274/4486090.html","https://www.booktxt.net/1_10274/4486092.html","https://www.booktxt.net/1_10274/4486094.html","https://www.booktxt.net/1_10274/4486096.html","https://www.booktxt.net/1_10274/4486098.html","https://www.booktxt.net/1_10274/4486100.html","https://www.booktxt.net/1_10274/4486101.html","https://www.booktxt.net/1_10274/4486103.html","https://www.booktxt.net/1_10274/4486105.html","https://www.booktxt.net/1_10274/4486107.html","https://www.booktxt.net/1_10274/4486109.html","https://www.booktxt.net/1_10274/4486110.html","https://www.booktxt.net/1_10274/4486112.html","https://www.booktxt.net/1_10274/4486114.html","https://www.booktxt.net/1_10274/4486116.html","https://www.booktxt.net/1_10274/4486118.html","https://www.booktxt.net/1_10274/4486120.html","https://www.booktxt.net/1_10274/4486122.html","https://www.booktxt.net/1_10274/4486124.html","https://www.booktxt.net/1_10274/4486126.html","https://www.booktxt.net/1_10274/4486128.html","https://www.booktxt.net/1_10274/4486130.html","https://www.booktxt.net/1_10274/4486131.html","https://www.booktxt.net/1_10274/4486133.html","https://www.booktxt.net/1_10274/4486135.html","https://www.booktxt.net/1_10274/4486137.html","https://www.booktxt.net/1_10274/4486139.html","https://www.booktxt.net/1_10274/4486141.html","https://www.booktxt.net/1_10274/4486143.html","https://www.booktxt.net/1_10274/4486145.html","https://www.booktxt.net/1_10274/4486147.html","https://www.booktxt.net/1_10274/4486149.html","https://www.booktxt.net/1_10274/4486151.html","https://www.booktxt.net/1_10274/4486153.html","https://www.booktxt.net/1_10274/4486155.html","https://www.booktxt.net/1_10274/4486157.html","https://www.booktxt.net/1_10274/4486159.html","https://www.booktxt.net/1_10274/4486161.html","https://www.booktxt.net/1_10274/4486163.html","https://www.booktxt.net/1_10274/4486165.html","https://www.booktxt.net/1_10274/4486167.html","https://www.booktxt.net/1_10274/4486169.html","https://www.booktxt.net/1_10274/4486171.html","https://www.booktxt.net/1_10274/4486173.html","https://www.booktxt.net/1_10274/4486175.html","https://www.booktxt.net/1_10274/4486176.html","https://www.booktxt.net/1_10274/4486178.html","https://www.booktxt.net/1_10274/4486180.html","https://www.booktxt.net/1_10274/4486182.html","https://www.booktxt.net/1_10274/4486184.html","https://www.booktxt.net/1_10274/4486186.html","https://www.booktxt.net/1_10274/4486188.html","https://www.booktxt.net/1_10274/4486190.html","https://www.booktxt.net/1_10274/4486192.html","https://www.booktxt.net/1_10274/4486194.html","https://www.booktxt.net/1_10274/4486196.html","https://www.booktxt.net/1_10274/4486197.html","https://www.booktxt.net/1_10274/4486199.html","https://www.booktxt.net/1_10274/4486200.html","https://www.booktxt.net/1_10274/4486202.html","https://www.booktxt.net/1_10274/4486204.html","https://www.booktxt.net/1_10274/4486206.html","https://www.booktxt.net/1_10274/4486208.html","https://www.booktxt.net/1_10274/4486210.html","https://www.booktxt.net/1_10274/4486212.html","https://www.booktxt.net/1_10274/4486213.html","https://www.booktxt.net/1_10274/4486215.html","https://www.booktxt.net/1_10274/4486217.html","https://www.booktxt.net/1_10274/4486219.html","https://www.booktxt.net/1_10274/4486221.html","https://www.booktxt.net/1_10274/4486223.html","https://www.booktxt.net/1_10274/4486225.html","https://www.booktxt.net/1_10274/4486227.html","https://www.booktxt.net/1_10274/4486229.html","https://www.booktxt.net/1_10274/4486231.html","https://www.booktxt.net/1_10274/4486233.html","https://www.booktxt.net/1_10274/4486235.html","https://www.booktxt.net/1_10274/4486237.html","https://www.booktxt.net/1_10274/4486238.html","https://www.booktxt.net/1_10274/4486240.html","https://www.booktxt.net/1_10274/4486242.html","https://www.booktxt.net/1_10274/4486244.html","https://www.booktxt.net/1_10274/4486245.html","https://www.booktxt.net/1_10274/4486247.html","https://www.booktxt.net/1_10274/4486249.html","https://www.booktxt.net/1_10274/4486251.html","https://www.booktxt.net/1_10274/4486253.html","https://www.booktxt.net/1_10274/4486255.html","https://www.booktxt.net/1_10274/4486257.html","https://www.booktxt.net/1_10274/4486258.html","https://www.booktxt.net/1_10274/4486261.html","https://www.booktxt.net/1_10274/4486263.html","https://www.booktxt.net/1_10274/4486265.html","https://www.booktxt.net/1_10274/4486266.html","https://www.booktxt.net/1_10274/4486269.html","https://www.booktxt.net/1_10274/4486271.html","https://www.booktxt.net/1_10274/4486273.html","https://www.booktxt.net/1_10274/4486275.html","https://www.booktxt.net/1_10274/4486277.html","https://www.booktxt.net/1_10274/4486279.html","https://www.booktxt.net/1_10274/4486281.html","https://www.booktxt.net/1_10274/4486282.html","https://www.booktxt.net/1_10274/4486284.html","https://www.booktxt.net/1_10274/4486286.html","https://www.booktxt.net/1_10274/4486288.html","https://www.booktxt.net/1_10274/4486291.html","https://www.booktxt.net/1_10274/4486293.html","https://www.booktxt.net/1_10274/4486295.html","https://www.booktxt.net/1_10274/4486296.html","https://www.booktxt.net/1_10274/4486298.html","https://www.booktxt.net/1_10274/4486300.html","https://www.booktxt.net/1_10274/4486302.html","https://www.booktxt.net/1_10274/4486304.html","https://www.booktxt.net/1_10274/4486306.html","https://www.booktxt.net/1_10274/4486308.html","https://www.booktxt.net/1_10274/4486309.html","https://www.booktxt.net/1_10274/4486311.html","https://www.booktxt.net/1_10274/4486313.html","https://www.booktxt.net/1_10274/4486315.html","https://www.booktxt.net/1_10274/4486317.html","https://www.booktxt.net/1_10274/4486319.html","https://www.booktxt.net/1_10274/4486321.html","https://www.booktxt.net/1_10274/4486323.html","https://www.booktxt.net/1_10274/4486325.html","https://www.booktxt.net/1_10274/4486326.html","https://www.booktxt.net/1_10274/4486328.html","https://www.booktxt.net/1_10274/4486330.html","https://www.booktxt.net/1_10274/4486332.html","https://www.booktxt.net/1_10274/4486334.html","https://www.booktxt.net/1_10274/4486336.html","https://www.booktxt.net/1_10274/4486338.html","https://www.booktxt.net/1_10274/4486340.html","https://www.booktxt.net/1_10274/4486342.html","https://www.booktxt.net/1_10274/4486343.html","https://www.booktxt.net/1_10274/4486345.html","https://www.booktxt.net/1_10274/4486347.html","https://www.booktxt.net/1_10274/4486349.html","https://www.booktxt.net/1_10274/4486351.html","https://www.booktxt.net/1_10274/4486353.html","https://www.booktxt.net/1_10274/4486355.html","https://www.booktxt.net/1_10274/4486357.html","https://www.booktxt.net/1_10274/4486359.html","https://www.booktxt.net/1_10274/4486360.html","https://www.booktxt.net/1_10274/4486362.html","https://www.booktxt.net/1_10274/4486364.html","https://www.booktxt.net/1_10274/4486367.html","https://www.booktxt.net/1_10274/4486369.html","https://www.booktxt.net/1_10274/4486371.html","https://www.booktxt.net/1_10274/4486373.html","https://www.booktxt.net/1_10274/4486375.html","https://www.booktxt.net/1_10274/4486377.html","https://www.booktxt.net/1_10274/4486379.html","https://www.booktxt.net/1_10274/4486381.html","https://www.booktxt.net/1_10274/4486383.html","https://www.booktxt.net/1_10274/4486385.html","https://www.booktxt.net/1_10274/4486387.html","https://www.booktxt.net/1_10274/4486389.html","https://www.booktxt.net/1_10274/4486391.html","https://www.booktxt.net/1_10274/4486393.html","https://www.booktxt.net/1_10274/4486395.html","https://www.booktxt.net/1_10274/4486397.html","https://www.booktxt.net/1_10274/4486399.html","https://www.booktxt.net/1_10274/4486400.html","https://www.booktxt.net/1_10274/4486402.html","https://www.booktxt.net/1_10274/4486404.html","https://www.booktxt.net/1_10274/4486406.html","https://www.booktxt.net/1_10274/4486408.html","https://www.booktxt.net/1_10274/4486410.html","https://www.booktxt.net/1_10274/4486412.html","https://www.booktxt.net/1_10274/4486414.html","https://www.booktxt.net/1_10274/4486416.html","https://www.booktxt.net/1_10274/4486417.html","https://www.booktxt.net/1_10274/4486419.html","https://www.booktxt.net/1_10274/4486421.html","https://www.booktxt.net/1_10274/4486423.html","https://www.booktxt.net/1_10274/4486425.html","https://www.booktxt.net/1_10274/4486427.html","https://www.booktxt.net/1_10274/4486429.html","https://www.booktxt.net/1_10274/4486431.html","https://www.booktxt.net/1_10274/4486433.html","https://www.booktxt.net/1_10274/4486435.html","https://www.booktxt.net/1_10274/4486437.html","https://www.booktxt.net/1_10274/4486439.html","https://www.booktxt.net/1_10274/4486441.html","https://www.booktxt.net/1_10274/4486442.html","https://www.booktxt.net/1_10274/4486444.html","https://www.booktxt.net/1_10274/4486446.html","https://www.booktxt.net/1_10274/4486448.html","https://www.booktxt.net/1_10274/4486450.html","https://www.booktxt.net/1_10274/4486453.html","https://www.booktxt.net/1_10274/4486454.html","https://www.booktxt.net/1_10274/4486456.html","https://www.booktxt.net/1_10274/4486458.html","https://www.booktxt.net/1_10274/4486460.html","https://www.booktxt.net/1_10274/4486462.html","https://www.booktxt.net/1_10274/4486464.html","https://www.booktxt.net/1_10274/4486466.html","https://www.booktxt.net/1_10274/4486468.html","https://www.booktxt.net/1_10274/4486470.html","https://www.booktxt.net/1_10274/4486472.html","https://www.booktxt.net/1_10274/4486473.html","https://www.booktxt.net/1_10274/4486475.html","https://www.booktxt.net/1_10274/4486477.html","https://www.booktxt.net/1_10274/4486479.html","https://www.booktxt.net/1_10274/4486481.html","https://www.booktxt.net/1_10274/4486483.html","https://www.booktxt.net/1_10274/4486485.html","https://www.booktxt.net/1_10274/4486487.html","https://www.booktxt.net/1_10274/4486489.html","https://www.booktxt.net/1_10274/4486491.html","https://www.booktxt.net/1_10274/4486493.html","https://www.booktxt.net/1_10274/4486495.html","https://www.booktxt.net/1_10274/4486497.html","https://www.booktxt.net/1_10274/4486499.html","https://www.booktxt.net/1_10274/4486501.html","https://www.booktxt.net/1_10274/4486503.html","https://www.booktxt.net/1_10274/4486504.html","https://www.booktxt.net/1_10274/4486506.html","https://www.booktxt.net/1_10274/4486508.html","https://www.booktxt.net/1_10274/4486510.html","https://www.booktxt.net/1_10274/4486512.html","https://www.booktxt.net/1_10274/4486514.html","https://www.booktxt.net/1_10274/4486516.html","https://www.booktxt.net/1_10274/4486518.html","https://www.booktxt.net/1_10274/4486520.html","https://www.booktxt.net/1_10274/4486521.html","https://www.booktxt.net/1_10274/4486523.html","https://www.booktxt.net/1_10274/4486525.html","https://www.booktxt.net/1_10274/4486526.html","https://www.booktxt.net/1_10274/4486528.html","https://www.booktxt.net/1_10274/4486530.html","https://www.booktxt.net/1_10274/4486532.html","https://www.booktxt.net/1_10274/4486534.html","https://www.booktxt.net/1_10274/4486536.html","https://www.booktxt.net/1_10274/4486538.html","https://www.booktxt.net/1_10274/4486540.html","https://www.booktxt.net/1_10274/4486542.html","https://www.booktxt.net/1_10274/4486544.html","https://www.booktxt.net/1_10274/4486546.html","https://www.booktxt.net/1_10274/4486548.html","https://www.booktxt.net/1_10274/4486550.html","https://www.booktxt.net/1_10274/4486551.html","https://www.booktxt.net/1_10274/4486553.html","https://www.booktxt.net/1_10274/4486555.html","https://www.booktxt.net/1_10274/4486557.html","https://www.booktxt.net/1_10274/4486559.html","https://www.booktxt.net/1_10274/4486561.html","https://www.booktxt.net/1_10274/4486563.html","https://www.booktxt.net/1_10274/4486565.html","https://www.booktxt.net/1_10274/4486566.html","https://www.booktxt.net/1_10274/4486568.html","https://www.booktxt.net/1_10274/4486570.html","https://www.booktxt.net/1_10274/4486572.html","https://www.booktxt.net/1_10274/4486574.html","https://www.booktxt.net/1_10274/4486576.html","https://www.booktxt.net/1_10274/4486578.html","https://www.booktxt.net/1_10274/4486580.html","https://www.booktxt.net/1_10274/4486582.html","https://www.booktxt.net/1_10274/4486583.html","https://www.booktxt.net/1_10274/4486585.html","https://www.booktxt.net/1_10274/4486587.html","https://www.booktxt.net/1_10274/4486589.html","https://www.booktxt.net/1_10274/4486591.html","https://www.booktxt.net/1_10274/4486593.html","https://www.booktxt.net/1_10274/4486594.html","https://www.booktxt.net/1_10274/4486596.html","https://www.booktxt.net/1_10274/4486598.html","https://www.booktxt.net/1_10274/4486600.html","https://www.booktxt.net/1_10274/4486602.html","https://www.booktxt.net/1_10274/4486604.html","https://www.booktxt.net/1_10274/4486606.html","https://www.booktxt.net/1_10274/4486608.html","https://www.booktxt.net/1_10274/4486610.html","https://www.booktxt.net/1_10274/4486612.html","https://www.booktxt.net/1_10274/4486614.html","https://www.booktxt.net/1_10274/4486615.html","https://www.booktxt.net/1_10274/4486617.html","https://www.booktxt.net/1_10274/4486619.html","https://www.booktxt.net/1_10274/4486621.html","https://www.booktxt.net/1_10274/4486623.html","https://www.booktxt.net/1_10274/4486625.html","https://www.booktxt.net/1_10274/4486627.html","https://www.booktxt.net/1_10274/4486629.html","https://www.booktxt.net/1_10274/4486631.html","https://www.booktxt.net/1_10274/4486633.html","https://www.booktxt.net/1_10274/4486635.html","https://www.booktxt.net/1_10274/4486637.html","https://www.booktxt.net/1_10274/4486638.html","https://www.booktxt.net/1_10274/4486640.html","https://www.booktxt.net/1_10274/4486642.html","https://www.booktxt.net/1_10274/4486644.html","https://www.booktxt.net/1_10274/4486646.html","https://www.booktxt.net/1_10274/4486648.html","https://www.booktxt.net/1_10274/4486650.html","https://www.booktxt.net/1_10274/4486652.html","https://www.booktxt.net/1_10274/4486654.html","https://www.booktxt.net/1_10274/4486655.html","https://www.booktxt.net/1_10274/4486657.html","https://www.booktxt.net/1_10274/4486659.html","https://www.booktxt.net/1_10274/4486661.html","https://www.booktxt.net/1_10274/4486663.html","https://www.booktxt.net/1_10274/4486664.html","https://www.booktxt.net/1_10274/4486666.html","https://www.booktxt.net/1_10274/4486668.html","https://www.booktxt.net/1_10274/4486670.html","https://www.booktxt.net/1_10274/4486672.html","https://www.booktxt.net/1_10274/4486674.html","https://www.booktxt.net/1_10274/4486676.html","https://www.booktxt.net/1_10274/4486678.html","https://www.booktxt.net/1_10274/4486680.html","https://www.booktxt.net/1_10274/4486681.html","https://www.booktxt.net/1_10274/4486683.html","https://www.booktxt.net/1_10274/4486685.html","https://www.booktxt.net/1_10274/4486687.html","https://www.booktxt.net/1_10274/4486689.html","https://www.booktxt.net/1_10274/4486691.html","https://www.booktxt.net/1_10274/4486693.html","https://www.booktxt.net/1_10274/4486694.html","https://www.booktxt.net/1_10274/4486696.html","https://www.booktxt.net/1_10274/4486698.html","https://www.booktxt.net/1_10274/4486700.html","https://www.booktxt.net/1_10274/4486702.html","https://www.booktxt.net/1_10274/4486704.html","https://www.booktxt.net/1_10274/4486706.html","https://www.booktxt.net/1_10274/4486708.html","https://www.booktxt.net/1_10274/4486710.html","https://www.booktxt.net/1_10274/4486712.html","https://www.booktxt.net/1_10274/4486713.html","https://www.booktxt.net/1_10274/4486715.html","https://www.booktxt.net/1_10274/4486717.html","https://www.booktxt.net/1_10274/4486719.html","https://www.booktxt.net/1_10274/4486721.html","https://www.booktxt.net/1_10274/4486723.html","https://www.booktxt.net/1_10274/4486725.html","https://www.booktxt.net/1_10274/4486727.html","https://www.booktxt.net/1_10274/4486729.html","https://www.booktxt.net/1_10274/4486731.html","https://www.booktxt.net/1_10274/4486733.html","https://www.booktxt.net/1_10274/4486735.html","https://www.booktxt.net/1_10274/4486736.html","https://www.booktxt.net/1_10274/4486738.html","https://www.booktxt.net/1_10274/4486740.html","https://www.booktxt.net/1_10274/4486742.html","https://www.booktxt.net/1_10274/4486744.html","https://www.booktxt.net/1_10274/4486746.html","https://www.booktxt.net/1_10274/4486748.html","https://www.booktxt.net/1_10274/4486750.html","https://www.booktxt.net/1_10274/4486752.html","https://www.booktxt.net/1_10274/4486754.html","https://www.booktxt.net/1_10274/4486756.html","https://www.booktxt.net/1_10274/4486757.html","https://www.booktxt.net/1_10274/4486759.html","https://www.booktxt.net/1_10274/4486761.html","https://www.booktxt.net/1_10274/4486763.html","https://www.booktxt.net/1_10274/4486765.html","https://www.booktxt.net/1_10274/4486767.html","https://www.booktxt.net/1_10274/4486769.html","https://www.booktxt.net/1_10274/4486771.html","https://www.booktxt.net/1_10274/4486773.html","https://www.booktxt.net/1_10274/4486775.html","https://www.booktxt.net/1_10274/4486777.html","https://www.booktxt.net/1_10274/4486778.html","https://www.booktxt.net/1_10274/4486780.html","https://www.booktxt.net/1_10274/4486782.html","https://www.booktxt.net/1_10274/4486784.html","https://www.booktxt.net/1_10274/4486786.html","https://www.booktxt.net/1_10274/4486788.html","https://www.booktxt.net/1_10274/4486790.html","https://www.booktxt.net/1_10274/4486792.html","https://www.booktxt.net/1_10274/4486793.html","https://www.booktxt.net/1_10274/4486795.html","https://www.booktxt.net/1_10274/4486797.html","https://www.booktxt.net/1_10274/4486799.html","https://www.booktxt.net/1_10274/4486801.html","https://www.booktxt.net/1_10274/4486803.html","https://www.booktxt.net/1_10274/4486805.html","https://www.booktxt.net/1_10274/4486806.html","https://www.booktxt.net/1_10274/4486808.html","https://www.booktxt.net/1_10274/4486810.html","https://www.booktxt.net/1_10274/4486812.html","https://www.booktxt.net/1_10274/4486814.html","https://www.booktxt.net/1_10274/4486816.html","https://www.booktxt.net/1_10274/4486818.html","https://www.booktxt.net/1_10274/4486821.html","https://www.booktxt.net/1_10274/4486822.html","https://www.booktxt.net/1_10274/4486824.html","https://www.booktxt.net/1_10274/4486826.html","https://www.booktxt.net/1_10274/4486828.html","https://www.booktxt.net/1_10274/4486830.html","https://www.booktxt.net/1_10274/4486832.html","https://www.booktxt.net/1_10274/4486834.html","https://www.booktxt.net/1_10274/4486836.html","https://www.booktxt.net/1_10274/4486837.html","https://www.booktxt.net/1_10274/4486839.html","https://www.booktxt.net/1_10274/4486841.html","https://www.booktxt.net/1_10274/4486843.html","https://www.booktxt.net/1_10274/4486845.html","https://www.booktxt.net/1_10274/4486847.html","https://www.booktxt.net/1_10274/4486849.html","https://www.booktxt.net/1_10274/4486851.html","https://www.booktxt.net/1_10274/4486853.html","https://www.booktxt.net/1_10274/4486854.html","https://www.booktxt.net/1_10274/4486856.html","https://www.booktxt.net/1_10274/4486858.html","https://www.booktxt.net/1_10274/4486860.html","https://www.booktxt.net/1_10274/4486862.html","https://www.booktxt.net/1_10274/4486864.html","https://www.booktxt.net/1_10274/4486866.html","https://www.booktxt.net/1_10274/4486867.html","https://www.booktxt.net/1_10274/4486869.html","https://www.booktxt.net/1_10274/4486871.html","https://www.booktxt.net/1_10274/4486873.html","https://www.booktxt.net/1_10274/4486875.html","https://www.booktxt.net/1_10274/4486877.html","https://www.booktxt.net/1_10274/4486879.html","https://www.booktxt.net/1_10274/4486881.html","https://www.booktxt.net/1_10274/4486882.html","https://www.booktxt.net/1_10274/4486884.html","https://www.booktxt.net/1_10274/4486886.html","https://www.booktxt.net/1_10274/4486888.html","https://www.booktxt.net/1_10274/4486891.html","https://www.booktxt.net/1_10274/4486895.html","https://www.booktxt.net/1_10274/4486898.html","https://www.booktxt.net/1_10274/4486902.html","https://www.booktxt.net/1_10274/4486904.html","https://www.booktxt.net/1_10274/4486908.html","https://www.booktxt.net/1_10274/4486912.html","https://www.booktxt.net/1_10274/4486916.html","https://www.booktxt.net/1_10274/4486918.html","https://www.booktxt.net/1_10274/4486921.html","https://www.booktxt.net/1_10274/4486925.html","https://www.booktxt.net/1_10274/4486928.html","https://www.booktxt.net/1_10274/4486932.html","https://www.booktxt.net/1_10274/4486936.html","https://www.booktxt.net/1_10274/4486940.html","https://www.booktxt.net/1_10274/4486943.html","https://www.booktxt.net/1_10274/4486947.html","https://www.booktxt.net/1_10274/4486950.html","https://www.booktxt.net/1_10274/4486954.html","https://www.booktxt.net/1_10274/4486958.html","https://www.booktxt.net/1_10274/4486962.html","https://www.booktxt.net/1_10274/4486965.html","https://www.booktxt.net/1_10274/4486969.html","https://www.booktxt.net/1_10274/4486973.html","https://www.booktxt.net/1_10274/4486976.html","https://www.booktxt.net/1_10274/4486980.html","https://www.booktxt.net/1_10274/4486983.html","https://www.booktxt.net/1_10274/4486988.html","https://www.booktxt.net/1_10274/4486991.html","https://www.booktxt.net/1_10274/4486995.html","https://www.booktxt.net/1_10274/4486999.html","https://www.booktxt.net/1_10274/4487002.html","https://www.booktxt.net/1_10274/4487006.html","https://www.booktxt.net/1_10274/4487010.html","https://www.booktxt.net/1_10274/4487015.html","https://www.booktxt.net/1_10274/4487017.html","https://www.booktxt.net/1_10274/4487018.html","https://www.booktxt.net/1_10274/4487019.html","https://www.booktxt.net/1_10274/4487022.html","https://www.booktxt.net/1_10274/4487024.html","https://www.booktxt.net/1_10274/4487028.html","https://www.booktxt.net/1_10274/4487032.html","https://www.booktxt.net/1_10274/4487036.html","https://www.booktxt.net/1_10274/4487040.html","https://www.booktxt.net/1_10274/4487044.html","https://www.booktxt.net/1_10274/4487049.html","https://www.booktxt.net/1_10274/4487053.html","https://www.booktxt.net/1_10274/4487057.html","https://www.booktxt.net/1_10274/4487061.html","https://www.booktxt.net/1_10274/4487066.html","https://www.booktxt.net/1_10274/4487072.html","https://www.booktxt.net/1_10274/4487078.html","https://www.booktxt.net/1_10274/4487083.html","https://www.booktxt.net/1_10274/4487089.html","https://www.booktxt.net/1_10274/4487094.html","https://www.booktxt.net/1_10274/4487099.html","https://www.booktxt.net/1_10274/4487102.html","https://www.booktxt.net/1_10274/4487107.html","https://www.booktxt.net/1_10274/4487112.html","https://www.booktxt.net/1_10274/4487117.html","https://www.booktxt.net/1_10274/4487120.html","https://www.booktxt.net/1_10274/4487126.html","https://www.booktxt.net/1_10274/4487132.html","https://www.booktxt.net/1_10274/4487138.html","https://www.booktxt.net/1_10274/4487144.html","https://www.booktxt.net/1_10274/4487148.html","https://www.booktxt.net/1_10274/4487154.html","https://www.booktxt.net/1_10274/4487157.html","https://www.booktxt.net/1_10274/4487162.html","https://www.booktxt.net/1_10274/4487167.html","https://www.booktxt.net/1_10274/4487171.html","https://www.booktxt.net/1_10274/4487175.html","https://www.booktxt.net/1_10274/4487181.html","https://www.booktxt.net/1_10274/4487186.html","https://www.booktxt.net/1_10274/4487190.html","https://www.booktxt.net/1_10274/4487196.html","https://www.booktxt.net/1_10274/4487201.html","https://www.booktxt.net/1_10274/4487206.html","https://www.booktxt.net/1_10274/4487210.html","https://www.booktxt.net/1_10274/4487216.html","https://www.booktxt.net/1_10274/4487222.html","https://www.booktxt.net/1_10274/4487227.html","https://www.booktxt.net/1_10274/4487233.html","https://www.booktxt.net/1_10274/4487238.html","https://www.booktxt.net/1_10274/4487244.html","https://www.booktxt.net/1_10274/4487249.html","https://www.booktxt.net/1_10274/4487254.html","https://www.booktxt.net/1_10274/4487259.html","https://www.booktxt.net/1_10274/4487265.html","https://www.booktxt.net/1_10274/4487271.html","https://www.booktxt.net/1_10274/4487276.html","https://www.booktxt.net/1_10274/4487281.html","https://www.booktxt.net/1_10274/4487287.html","https://www.booktxt.net/1_10274/4487290.html","https://www.booktxt.net/1_10274/4487295.html","https://www.booktxt.net/1_10274/4487300.html","https://www.booktxt.net/1_10274/4487305.html","https://www.booktxt.net/1_10274/4487308.html","https://www.booktxt.net/1_10274/4487314.html","https://www.booktxt.net/1_10274/4487318.html","https://www.booktxt.net/1_10274/4487321.html","https://www.booktxt.net/1_10274/4487324.html","https://www.booktxt.net/1_10274/4487328.html","https://www.booktxt.net/1_10274/4487331.html","https://www.booktxt.net/1_10274/4487335.html","https://www.booktxt.net/1_10274/4487339.html","https://www.booktxt.net/1_10274/4487341.html","https://www.booktxt.net/1_10274/4487345.html","https://www.booktxt.net/1_10274/4487348.html","https://www.booktxt.net/1_10274/4487352.html","https://www.booktxt.net/1_10274/4487355.html","https://www.booktxt.net/1_10274/4487359.html","https://www.booktxt.net/1_10274/4487361.html","https://www.booktxt.net/1_10274/4487363.html","https://www.booktxt.net/1_10274/4487366.html","https://www.booktxt.net/1_10274/4487370.html","https://www.booktxt.net/1_10274/4487373.html","https://www.booktxt.net/1_10274/4487377.html","https://www.booktxt.net/1_10274/4487380.html","https://www.booktxt.net/1_10274/4487384.html","https://www.booktxt.net/1_10274/4487386.html","https://www.booktxt.net/1_10274/4487390.html","https://www.booktxt.net/1_10274/4487393.html","https://www.booktxt.net/1_10274/4487397.html","https://www.booktxt.net/1_10274/4487401.html","https://www.booktxt.net/1_10274/4487404.html","https://www.booktxt.net/1_10274/4487408.html","https://www.booktxt.net/1_10274/4487411.html","https://www.booktxt.net/1_10274/4487415.html","https://www.booktxt.net/1_10274/4487418.html","https://www.booktxt.net/1_10274/4487422.html","https://www.booktxt.net/1_10274/4487425.html","https://www.booktxt.net/1_10274/4487428.html","https://www.booktxt.net/1_10274/4487432.html","https://www.booktxt.net/1_10274/4487435.html","https://www.booktxt.net/1_10274/4487439.html","https://www.booktxt.net/1_10274/4487442.html","https://www.booktxt.net/1_10274/4487446.html","https://www.booktxt.net/1_10274/4487448.html","https://www.booktxt.net/1_10274/4487452.html","https://www.booktxt.net/1_10274/4487455.html","https://www.booktxt.net/1_10274/4487459.html","https://www.booktxt.net/1_10274/4487462.html","https://www.booktxt.net/1_10274/4487466.html","https://www.booktxt.net/1_10274/4487470.html","https://www.booktxt.net/1_10274/4487472.html","https://www.booktxt.net/1_10274/4487476.html","https://www.booktxt.net/1_10274/4487479.html","https://www.booktxt.net/1_10274/4487483.html","https://www.booktxt.net/1_10274/4487486.html","https://www.booktxt.net/1_10274/4487490.html","https://www.booktxt.net/1_10274/4487492.html","https://www.booktxt.net/1_10274/4487496.html","https://www.booktxt.net/1_10274/4487499.html","https://www.booktxt.net/1_10274/4487503.html","https://www.booktxt.net/1_10274/4487506.html","https://www.booktxt.net/1_10274/4487510.html","https://www.booktxt.net/1_10274/4487512.html","https://www.booktxt.net/1_10274/4487516.html","https://www.booktxt.net/1_10274/4487519.html","https://www.booktxt.net/1_10274/4487523.html","https://www.booktxt.net/1_10274/4487526.html","https://www.booktxt.net/1_10274/4487530.html","https://www.booktxt.net/1_10274/4487533.html","https://www.booktxt.net/1_10274/4487537.html","https://www.booktxt.net/1_10274/4487540.html","https://www.booktxt.net/1_10274/4487543.html","https://www.booktxt.net/1_10274/4487546.html","https://www.booktxt.net/1_10274/4487550.html","https://www.booktxt.net/1_10274/4487554.html","https://www.booktxt.net/1_10274/4487556.html","https://www.booktxt.net/1_10274/4487559.html","https://www.booktxt.net/1_10274/4487564.html","https://www.booktxt.net/1_10274/4487570.html","https://www.booktxt.net/1_10274/4487574.html","https://www.booktxt.net/1_10274/4487580.html","https://www.booktxt.net/1_10274/4487584.html","https://www.booktxt.net/1_10274/4487587.html","https://www.booktxt.net/1_10274/4487591.html","https://www.booktxt.net/1_10274/4487594.html","https://www.booktxt.net/1_10274/4487598.html","https://www.booktxt.net/1_10274/4487601.html","https://www.booktxt.net/1_10274/4487605.html","https://www.booktxt.net/1_10274/4487607.html","https://www.booktxt.net/1_10274/4487611.html","https://www.booktxt.net/1_10274/4487614.html","https://www.booktxt.net/1_10274/4487617.html","https://www.booktxt.net/1_10274/4487621.html","https://www.booktxt.net/1_10274/4487624.html","https://www.booktxt.net/1_10274/4487628.html","https://www.booktxt.net/1_10274/4487631.html","https://www.booktxt.net/1_10274/4487634.html","https://www.booktxt.net/1_10274/4487637.html","https://www.booktxt.net/1_10274/4487641.html","https://www.booktxt.net/1_10274/4487644.html","https://www.booktxt.net/1_10274/4487646.html","https://www.booktxt.net/1_10274/4487649.html","https://www.booktxt.net/1_10274/4487652.html","https://www.booktxt.net/1_10274/4487656.html","https://www.booktxt.net/1_10274/4487659.html","https://www.booktxt.net/1_10274/4487663.html","https://www.booktxt.net/1_10274/4487666.html","https://www.booktxt.net/1_10274/4487670.html","https://www.booktxt.net/1_10274/4487673.html","https://www.booktxt.net/1_10274/4487676.html","https://www.booktxt.net/1_10274/4487679.html","https://www.booktxt.net/1_10274/4487683.html","https://www.booktxt.net/1_10274/4487687.html","https://www.booktxt.net/1_10274/4487691.html","https://www.booktxt.net/1_10274/4487694.html","https://www.booktxt.net/1_10274/4487698.html","https://www.booktxt.net/1_10274/4487700.html","https://www.booktxt.net/1_10274/4487704.html","https://www.booktxt.net/1_10274/4487708.html","https://www.booktxt.net/1_10274/4487712.html","https://www.booktxt.net/1_10274/4487715.html","https://www.booktxt.net/1_10274/4487717.html","https://www.booktxt.net/1_10274/4487720.html","https://www.booktxt.net/1_10274/4487724.html","https://www.booktxt.net/1_10274/4487727.html","https://www.booktxt.net/1_10274/4487731.html","https://www.booktxt.net/1_10274/4487734.html","https://www.booktxt.net/1_10274/4487738.html","https://www.booktxt.net/1_10274/4487742.html","https://www.booktxt.net/1_10274/4487746.html","https://www.booktxt.net/1_10274/4487750.html","https://www.booktxt.net/1_10274/4487754.html","https://www.booktxt.net/1_10274/4487758.html","https://www.booktxt.net/1_10274/4487762.html","https://www.booktxt.net/1_10274/4487766.html","https://www.booktxt.net/1_10274/4487769.html","https://www.booktxt.net/1_10274/4487771.html","https://www.booktxt.net/1_10274/4487774.html","https://www.booktxt.net/1_10274/4487780.html","https://www.booktxt.net/1_10274/4487784.html","https://www.booktxt.net/1_10274/4487787.html","https://www.booktxt.net/1_10274/4487790.html","https://www.booktxt.net/1_10274/4487794.html","https://www.booktxt.net/1_10274/4487797.html","https://www.booktxt.net/1_10274/4487801.html","https://www.booktxt.net/1_10274/4487805.html","https://www.booktxt.net/1_10274/4487808.html","https://www.booktxt.net/1_10274/4487811.html","https://www.booktxt.net/1_10274/4487816.html","https://www.booktxt.net/1_10274/4487819.html","https://www.booktxt.net/1_10274/4487823.html","https://www.booktxt.net/1_10274/4487827.html","https://www.booktxt.net/1_10274/4487831.html","https://www.booktxt.net/1_10274/4487835.html","https://www.booktxt.net/1_10274/4487838.html","https://www.booktxt.net/1_10274/4487841.html","https://www.booktxt.net/1_10274/4487845.html","https://www.booktxt.net/1_10274/4487849.html","https://www.booktxt.net/1_10274/4487853.html","https://www.booktxt.net/1_10274/4487858.html","https://www.booktxt.net/1_10274/4487862.html","https://www.booktxt.net/1_10274/4487866.html","https://www.booktxt.net/1_10274/4487870.html","https://www.booktxt.net/1_10274/4487872.html","https://www.booktxt.net/1_10274/4487876.html","https://www.booktxt.net/1_10274/4487880.html","https://www.booktxt.net/1_10274/4487883.html","https://www.booktxt.net/1_10274/4487887.html","https://www.booktxt.net/1_10274/4487892.html","https://www.booktxt.net/1_10274/4487894.html","https://www.booktxt.net/1_10274/4487898.html","https://www.booktxt.net/1_10274/4487902.html","https://www.booktxt.net/1_10274/4487906.html","https://www.booktxt.net/1_10274/4487910.html","https://www.booktxt.net/1_10274/4487914.html","https://www.booktxt.net/1_10274/4487918.html","https://www.booktxt.net/1_10274/4487921.html","https://www.booktxt.net/1_10274/4487925.html","https://www.booktxt.net/1_10274/4487928.html","https://www.booktxt.net/1_10274/4487931.html","https://www.booktxt.net/1_10274/4487936.html","https://www.booktxt.net/1_10274/4487940.html","https://www.booktxt.net/1_10274/4487944.html","https://www.booktxt.net/1_10274/4487948.html","https://www.booktxt.net/1_10274/4487952.html","https://www.booktxt.net/1_10274/4487954.html","https://www.booktxt.net/1_10274/4487958.html","https://www.booktxt.net/1_10274/4487962.html","https://www.booktxt.net/1_10274/4487965.html","https://www.booktxt.net/1_10274/4487969.html","https://www.booktxt.net/1_10274/4487973.html","https://www.booktxt.net/1_10274/4487978.html","https://www.booktxt.net/1_10274/4487981.html","https://www.booktxt.net/1_10274/4487983.html","https://www.booktxt.net/1_10274/4487985.html","https://www.booktxt.net/1_10274/4487987.html","https://www.booktxt.net/1_10274/4487989.html","https://www.booktxt.net/1_10274/4487991.html","https://www.booktxt.net/1_10274/4487993.html","https://www.booktxt.net/1_10274/4487996.html","https://www.booktxt.net/1_10274/4487998.html","https://www.booktxt.net/1_10274/4488000.html","https://www.booktxt.net/1_10274/4488002.html","https://www.booktxt.net/1_10274/4488003.html","https://www.booktxt.net/1_10274/4488005.html","https://www.booktxt.net/1_10274/4488008.html","https://www.booktxt.net/1_10274/4488010.html","https://www.booktxt.net/1_10274/4488012.html","https://www.booktxt.net/1_10274/4488014.html","https://www.booktxt.net/1_10274/4488016.html","https://www.booktxt.net/1_10274/4488017.html","https://www.booktxt.net/1_10274/4488019.html","https://www.booktxt.net/1_10274/4488021.html","https://www.booktxt.net/1_10274/4488023.html","https://www.booktxt.net/1_10274/4488025.html","https://www.booktxt.net/1_10274/4488027.html","https://www.booktxt.net/1_10274/4488029.html","https://www.booktxt.net/1_10274/4488031.html","https://www.booktxt.net/1_10274/4488033.html","https://www.booktxt.net/1_10274/4488035.html","https://www.booktxt.net/1_10274/4488037.html","https://www.booktxt.net/1_10274/4488038.html","https://www.booktxt.net/1_10274/4488040.html","https://www.booktxt.net/1_10274/4488042.html","https://www.booktxt.net/1_10274/4488044.html","https://www.booktxt.net/1_10274/4488046.html","https://www.booktxt.net/1_10274/4488048.html","https://www.booktxt.net/1_10274/4488050.html","https://www.booktxt.net/1_10274/4488052.html","https://www.booktxt.net/1_10274/4488054.html","https://www.booktxt.net/1_10274/4488056.html","https://www.booktxt.net/1_10274/4488058.html","https://www.booktxt.net/1_10274/4488059.html","https://www.booktxt.net/1_10274/4488061.html","https://www.booktxt.net/1_10274/4488063.html","https://www.booktxt.net/1_10274/4488065.html","https://www.booktxt.net/1_10274/4488067.html","https://www.booktxt.net/1_10274/4488069.html","https://www.booktxt.net/1_10274/4488071.html","https://www.booktxt.net/1_10274/4488073.html","https://www.booktxt.net/1_10274/4488075.html","https://www.booktxt.net/1_10274/4488077.html","https://www.booktxt.net/1_10274/4488079.html","https://www.booktxt.net/1_10274/4488081.html","https://www.booktxt.net/1_10274/4488083.html","https://www.booktxt.net/1_10274/4488085.html","https://www.booktxt.net/1_10274/4488087.html","https://www.booktxt.net/1_10274/4488089.html","https://www.booktxt.net/1_10274/4488091.html","https://www.booktxt.net/1_10274/4488093.html","https://www.booktxt.net/1_10274/4488095.html","https://www.booktxt.net/1_10274/4488097.html","https://www.booktxt.net/1_10274/4488099.html","https://www.booktxt.net/1_10274/4488100.html","https://www.booktxt.net/1_10274/4488101.html","https://www.booktxt.net/1_10274/4488102.html","https://www.booktxt.net/1_10274/4488103.html","https://www.booktxt.net/1_10274/4488104.html","https://www.booktxt.net/1_10274/4488105.html","https://www.booktxt.net/1_10274/4488106.html","https://www.booktxt.net/1_10274/4488107.html","https://www.booktxt.net/1_10274/4488108.html","https://www.booktxt.net/1_10274/4488109.html","https://www.booktxt.net/1_10274/4488110.html","https://www.booktxt.net/1_10274/4488111.html","https://www.booktxt.net/1_10274/4488112.html","https://www.booktxt.net/1_10274/4488113.html","https://www.booktxt.net/1_10274/4488114.html","https://www.booktxt.net/1_10274/4488115.html","https://www.booktxt.net/1_10274/4488116.html","https://www.booktxt.net/1_10274/4488117.html","https://www.booktxt.net/1_10274/4488118.html","https://www.booktxt.net/1_10274/4488119.html","https://www.booktxt.net/1_10274/4488120.html","https://www.booktxt.net/1_10274/4488121.html","https://www.booktxt.net/1_10274/4488122.html","https://www.booktxt.net/1_10274/4488123.html","https://www.booktxt.net/1_10274/4488124.html","https://www.booktxt.net/1_10274/4488126.html","https://www.booktxt.net/1_10274/4488127.html","https://www.booktxt.net/1_10274/4488128.html","https://www.booktxt.net/1_10274/4488129.html","https://www.booktxt.net/1_10274/4488130.html","https://www.booktxt.net/1_10274/4488131.html","https://www.booktxt.net/1_10274/4488132.html","https://www.booktxt.net/1_10274/4488133.html","https://www.booktxt.net/1_10274/4488134.html","https://www.booktxt.net/1_10274/4488135.html","https://www.booktxt.net/1_10274/4488137.html","https://www.booktxt.net/1_10274/4488138.html","https://www.booktxt.net/1_10274/4488139.html","https://www.booktxt.net/1_10274/4488140.html","https://www.booktxt.net/1_10274/4488141.html","https://www.booktxt.net/1_10274/4488142.html","https://www.booktxt.net/1_10274/4488143.html","https://www.booktxt.net/1_10274/4488144.html","https://www.booktxt.net/1_10274/4488145.html","https://www.booktxt.net/1_10274/4488146.html","https://www.booktxt.net/1_10274/4488148.html","https://www.booktxt.net/1_10274/4488149.html","https://www.booktxt.net/1_10274/4488150.html","https://www.booktxt.net/1_10274/4488151.html","https://www.booktxt.net/1_10274/4488152.html","https://www.booktxt.net/1_10274/4488153.html","https://www.booktxt.net/1_10274/4488154.html","https://www.booktxt.net/1_10274/4488155.html","https://www.booktxt.net/1_10274/4488156.html","https://www.booktxt.net/1_10274/4488157.html","https://www.booktxt.net/1_10274/4488158.html","https://www.booktxt.net/1_10274/4488160.html","https://www.booktxt.net/1_10274/4488161.html","https://www.booktxt.net/1_10274/4488162.html","https://www.booktxt.net/1_10274/4488163.html","https://www.booktxt.net/1_10274/4488164.html","https://www.booktxt.net/1_10274/4488165.html","https://www.booktxt.net/1_10274/4488166.html","https://www.booktxt.net/1_10274/4488167.html","https://www.booktxt.net/1_10274/4488168.html","https://www.booktxt.net/1_10274/4488169.html","https://www.booktxt.net/1_10274/4488171.html","https://www.booktxt.net/1_10274/4488172.html","https://www.booktxt.net/1_10274/4488173.html","https://www.booktxt.net/1_10274/4488174.html","https://www.booktxt.net/1_10274/4488175.html","https://www.booktxt.net/1_10274/4488176.html","https://www.booktxt.net/1_10274/4488177.html","https://www.booktxt.net/1_10274/4488178.html","https://www.booktxt.net/1_10274/4488179.html","https://www.booktxt.net/1_10274/4488180.html","https://www.booktxt.net/1_10274/4488181.html","https://www.booktxt.net/1_10274/4488183.html","https://www.booktxt.net/1_10274/4488184.html","https://www.booktxt.net/1_10274/4488185.html","https://www.booktxt.net/1_10274/4488186.html","https://www.booktxt.net/1_10274/4488187.html","https://www.booktxt.net/1_10274/4488188.html","https://www.booktxt.net/1_10274/4488189.html","https://www.booktxt.net/1_10274/4488190.html","https://www.booktxt.net/1_10274/4488192.html","https://www.booktxt.net/1_10274/4488193.html","https://www.booktxt.net/1_10274/4488194.html","https://www.booktxt.net/1_10274/4488195.html","https://www.booktxt.net/1_10274/4488196.html","https://www.booktxt.net/1_10274/4488197.html","https://www.booktxt.net/1_10274/4488198.html","https://www.booktxt.net/1_10274/4488199.html","https://www.booktxt.net/1_10274/4488201.html","https://www.booktxt.net/1_10274/4488202.html","https://www.booktxt.net/1_10274/4488203.html","https://www.booktxt.net/1_10274/4488204.html","https://www.booktxt.net/1_10274/4488205.html","https://www.booktxt.net/1_10274/4488206.html","https://www.booktxt.net/1_10274/4488208.html","https://www.booktxt.net/1_10274/4488209.html","https://www.booktxt.net/1_10274/4488210.html","https://www.booktxt.net/1_10274/4488211.html","https://www.booktxt.net/1_10274/4488212.html","https://www.booktxt.net/1_10274/4488213.html","https://www.booktxt.net/1_10274/4488214.html","https://www.booktxt.net/1_10274/4488216.html","https://www.booktxt.net/1_10274/4488217.html","https://www.booktxt.net/1_10274/4488218.html","https://www.booktxt.net/1_10274/4488219.html","https://www.booktxt.net/1_10274/4488220.html","https://www.booktxt.net/1_10274/4488221.html","https://www.booktxt.net/1_10274/4488222.html","https://www.booktxt.net/1_10274/4488224.html","https://www.booktxt.net/1_10274/4488225.html","https://www.booktxt.net/1_10274/4488226.html","https://www.booktxt.net/1_10274/4488227.html","https://www.booktxt.net/1_10274/4488228.html","https://www.booktxt.net/1_10274/4488229.html","https://www.booktxt.net/1_10274/4488230.html","https://www.booktxt.net/1_10274/4488231.html","https://www.booktxt.net/1_10274/4488232.html","https://www.booktxt.net/1_10274/4488234.html","https://www.booktxt.net/1_10274/4488235.html","https://www.booktxt.net/1_10274/4488236.html","https://www.booktxt.net/1_10274/4488237.html","https://www.booktxt.net/1_10274/4488238.html","https://www.booktxt.net/1_10274/4488239.html","https://www.booktxt.net/1_10274/4488240.html","https://www.booktxt.net/1_10274/4488241.html","https://www.booktxt.net/1_10274/4488242.html","https://www.booktxt.net/1_10274/4488243.html","https://www.booktxt.net/1_10274/4488245.html","https://www.booktxt.net/1_10274/4488246.html","https://www.booktxt.net/1_10274/4488247.html","https://www.booktxt.net/1_10274/4488248.html","https://www.booktxt.net/1_10274/4488249.html","https://www.booktxt.net/1_10274/4488250.html","https://www.booktxt.net/1_10274/4488251.html","https://www.booktxt.net/1_10274/4488252.html","https://www.booktxt.net/1_10274/4488253.html","https://www.booktxt.net/1_10274/4488255.html","https://www.booktxt.net/1_10274/4488256.html","https://www.booktxt.net/1_10274/4488257.html","https://www.booktxt.net/1_10274/4488258.html","https://www.booktxt.net/1_10274/4488259.html","https://www.booktxt.net/1_10274/4488260.html","https://www.booktxt.net/1_10274/4488261.html","https://www.booktxt.net/1_10274/4488262.html","https://www.booktxt.net/1_10274/4488263.html","https://www.booktxt.net/1_10274/4488264.html","https://www.booktxt.net/1_10274/4488266.html","https://www.booktxt.net/1_10274/4488267.html","https://www.booktxt.net/1_10274/4488268.html","https://www.booktxt.net/1_10274/4488269.html","https://www.booktxt.net/1_10274/4488270.html","https://www.booktxt.net/1_10274/4488271.html","https://www.booktxt.net/1_10274/4488272.html","https://www.booktxt.net/1_10274/4488273.html","https://www.booktxt.net/1_10274/4488274.html","https://www.booktxt.net/1_10274/4488275.html","https://www.booktxt.net/1_10274/4488276.html","https://www.booktxt.net/1_10274/4488278.html","https://www.booktxt.net/1_10274/4488279.html","https://www.booktxt.net/1_10274/4488280.html","https://www.booktxt.net/1_10274/4488281.html","https://www.booktxt.net/1_10274/4488282.html","https://www.booktxt.net/1_10274/4488283.html","https://www.booktxt.net/1_10274/4488284.html","https://www.booktxt.net/1_10274/4488285.html","https://www.booktxt.net/1_10274/4488287.html","https://www.booktxt.net/1_10274/4488288.html","https://www.booktxt.net/1_10274/4488289.html","https://www.booktxt.net/1_10274/4488290.html","https://www.booktxt.net/1_10274/4488291.html","https://www.booktxt.net/1_10274/4488292.html","https://www.booktxt.net/1_10274/4488293.html","https://www.booktxt.net/1_10274/4488294.html","https://www.booktxt.net/1_10274/4488295.html","https://www.booktxt.net/1_10274/4488296.html","https://www.booktxt.net/1_10274/4488298.html","https://www.booktxt.net/1_10274/4488299.html","https://www.booktxt.net/1_10274/4488300.html","https://www.booktxt.net/1_10274/4488301.html","https://www.booktxt.net/1_10274/4488302.html","https://www.booktxt.net/1_10274/4488303.html","https://www.booktxt.net/1_10274/4488304.html","https://www.booktxt.net/1_10274/4488305.html","https://www.booktxt.net/1_10274/4488306.html","https://www.booktxt.net/1_10274/4488307.html","https://www.booktxt.net/1_10274/4488309.html","https://www.booktxt.net/1_10274/4488310.html","https://www.booktxt.net/1_10274/4488311.html","https://www.booktxt.net/1_10274/4488312.html","https://www.booktxt.net/1_10274/4488313.html","https://www.booktxt.net/1_10274/4488314.html","https://www.booktxt.net/1_10274/4488315.html","https://www.booktxt.net/1_10274/4488316.html","https://www.booktxt.net/1_10274/4488317.html","https://www.booktxt.net/1_10274/4488318.html","https://www.booktxt.net/1_10274/4488319.html","https://www.booktxt.net/1_10274/4488320.html","https://www.booktxt.net/1_10274/4488321.html","https://www.booktxt.net/1_10274/4488322.html","https://www.booktxt.net/1_10274/4488323.html","https://www.booktxt.net/1_10274/4488324.html","https://www.booktxt.net/1_10274/4488325.html","https://www.booktxt.net/1_10274/4488326.html","https://www.booktxt.net/1_10274/4488327.html","https://www.booktxt.net/1_10274/4488328.html","https://www.booktxt.net/1_10274/4488329.html","https://www.booktxt.net/1_10274/4488330.html","https://www.booktxt.net/1_10274/4488331.html","https://www.booktxt.net/1_10274/4488332.html","https://www.booktxt.net/1_10274/4488333.html","https://www.booktxt.net/1_10274/4488334.html","https://www.booktxt.net/1_10274/4488335.html","https://www.booktxt.net/1_10274/4488336.html","https://www.booktxt.net/1_10274/4488337.html","https://www.booktxt.net/1_10274/4488338.html","https://www.booktxt.net/1_10274/4488339.html","https://www.booktxt.net/1_10274/4488340.html","https://www.booktxt.net/1_10274/4488341.html","https://www.booktxt.net/1_10274/4488342.html","https://www.booktxt.net/1_10274/4488343.html","https://www.booktxt.net/1_10274/4488344.html","https://www.booktxt.net/1_10274/4488345.html","https://www.booktxt.net/1_10274/4488346.html","https://www.booktxt.net/1_10274/4488347.html","https://www.booktxt.net/1_10274/4488348.html","https://www.booktxt.net/1_10274/4488349.html","https://www.booktxt.net/1_10274/4488350.html","https://www.booktxt.net/1_10274/4488351.html","https://www.booktxt.net/1_10274/4488352.html","https://www.booktxt.net/1_10274/4488353.html","https://www.booktxt.net/1_10274/4488354.html","https://www.booktxt.net/1_10274/4488355.html","https://www.booktxt.net/1_10274/4488356.html","https://www.booktxt.net/1_10274/4488357.html","https://www.booktxt.net/1_10274/4497817.html","https://www.booktxt.net/1_10274/4497818.html","https://www.booktxt.net/1_10274/4499457.html","https://www.booktxt.net/1_10274/4499942.html","https://www.booktxt.net/1_10274/4500622.html","https://www.booktxt.net/1_10274/4503868.html","https://www.booktxt.net/1_10274/4505720.html","https://www.booktxt.net/1_10274/4506083.html","https://www.booktxt.net/1_10274/4506725.html","https://www.booktxt.net/1_10274/4507079.html","https://www.booktxt.net/1_10274/4508810.html","https://www.booktxt.net/1_10274/4521238.html","https://www.booktxt.net/1_10274/4521712.html","https://www.booktxt.net/1_10274/4522265.html","https://www.booktxt.net/1_10274/4523230.html","https://www.booktxt.net/1_10274/4530605.html","https://www.booktxt.net/1_10274/4534123.html","https://www.booktxt.net/1_10274/4534651.html","https://www.booktxt.net/1_10274/4535323.html","https://www.booktxt.net/1_10274/4555786.html","https://www.booktxt.net/1_10274/4556733.html","https://www.booktxt.net/1_10274/4557968.html","https://www.booktxt.net/1_10274/4558355.html","https://www.booktxt.net/1_10274/4558775.html","https://www.booktxt.net/1_10274/4559142.html","https://www.booktxt.net/1_10274/4559963.html","https://www.booktxt.net/1_10274/4560990.html","https://www.booktxt.net/1_10274/4561319.html","https://www.booktxt.net/1_10274/4561677.html","https://www.booktxt.net/1_10274/4562000.html","https://www.booktxt.net/1_10274/4562579.html","https://www.booktxt.net/1_10274/4564191.html","https://www.booktxt.net/1_10274/4564574.html","https://www.booktxt.net/1_10274/4564956.html","https://www.booktxt.net/1_10274/4565501.html","https://www.booktxt.net/1_10274/4566108.html","https://www.booktxt.net/1_10274/4567434.html","https://www.booktxt.net/1_10274/4569675.html","https://www.booktxt.net/1_10274/4569676.html","https://www.booktxt.net/1_10274/4569677.html","https://www.booktxt.net/1_10274/4569678.html","https://www.booktxt.net/1_10274/4573740.html","https://www.booktxt.net/1_10274/4574054.html","https://www.booktxt.net/1_10274/4574289.html","https://www.booktxt.net/1_10274/4574976.html","https://www.booktxt.net/1_10274/4575372.html","https://www.booktxt.net/1_10274/4576279.html","https://www.booktxt.net/1_10274/4576912.html","https://www.booktxt.net/1_10274/4577437.html","https://www.booktxt.net/1_10274/4578347.html","https://www.booktxt.net/1_10274/4578448.html","https://www.booktxt.net/1_10274/4579334.html","https://www.booktxt.net/1_10274/4579665.html","https://www.booktxt.net/1_10274/4580141.html","https://www.booktxt.net/1_10274/4580649.html","https://www.booktxt.net/1_10274/4581464.html","https://www.booktxt.net/1_10274/4582502.html","https://www.booktxt.net/1_10274/4582612.html","https://www.booktxt.net/1_10274/4583336.html","https://www.booktxt.net/1_10274/4583573.html","https://www.booktxt.net/1_10274/4585054.html","https://www.booktxt.net/1_10274/4587188.html","https://www.booktxt.net/1_10274/4587379.html","https://www.booktxt.net/1_10274/4587659.html","https://www.booktxt.net/1_10274/4587914.html","https://www.booktxt.net/1_10274/4588202.html","https://www.booktxt.net/1_10274/4590381.html","https://www.booktxt.net/1_10274/4590482.html","https://www.booktxt.net/1_10274/4590620.html","https://www.booktxt.net/1_10274/4590679.html","https://www.booktxt.net/1_10274/4590850.html","https://www.booktxt.net/1_10274/4593132.html","https://www.booktxt.net/1_10274/4593312.html","https://www.booktxt.net/1_10274/4593313.html","https://www.booktxt.net/1_10274/4593330.html","https://www.booktxt.net/1_10274/4593354.html","https://www.booktxt.net/1_10274/4595677.html","https://www.booktxt.net/1_10274/4595884.html","https://www.booktxt.net/1_10274/4596071.html","https://www.booktxt.net/1_10274/4596098.html","https://www.booktxt.net/1_10274/4596151.html","https://www.booktxt.net/1_10274/4599837.html","https://www.booktxt.net/1_10274/4599941.html","https://www.booktxt.net/1_10274/4600195.html","https://www.booktxt.net/1_10274/4600416.html","https://www.booktxt.net/1_10274/4600552.html","https://www.booktxt.net/1_10274/4602698.html","https://www.booktxt.net/1_10274/4602930.html","https://www.booktxt.net/1_10274/4603105.html","https://www.booktxt.net/1_10274/4603296.html","https://www.booktxt.net/1_10274/4603324.html","https://www.booktxt.net/1_10274/4605608.html","https://www.booktxt.net/1_10274/4605710.html","https://www.booktxt.net/1_10274/4605793.html","https://www.booktxt.net/1_10274/4605927.html","https://www.booktxt.net/1_10274/4606142.html","https://www.booktxt.net/1_10274/4606206.html","https://www.booktxt.net/1_10274/4606271.html","https://www.booktxt.net/1_10274/4606421.html","https://www.booktxt.net/1_10274/4606466.html","https://www.booktxt.net/1_10274/4606804.html","https://www.booktxt.net/1_10274/4609435.html","https://www.booktxt.net/1_10274/4609534.html","https://www.booktxt.net/1_10274/4609683.html","https://www.booktxt.net/1_10274/4609923.html","https://www.booktxt.net/1_10274/4610304.html","https://www.booktxt.net/1_10274/4611853.html","https://www.booktxt.net/1_10274/4612429.html","https://www.booktxt.net/1_10274/4612640.html","https://www.booktxt.net/1_10274/4613334.html","https://www.booktxt.net/1_10274/4613635.html","https://www.booktxt.net/1_10274/4615686.html","https://www.booktxt.net/1_10274/4616047.html","https://www.booktxt.net/1_10274/4616661.html","https://www.booktxt.net/1_10274/4617028.html","https://www.booktxt.net/1_10274/4617634.html","https://www.booktxt.net/1_10274/4619152.html","https://www.booktxt.net/1_10274/4619540.html","https://www.booktxt.net/1_10274/4619790.html","https://www.booktxt.net/1_10274/4620112.html","https://www.booktxt.net/1_10274/4620673.html","https://www.booktxt.net/1_10274/4622631.html","https://www.booktxt.net/1_10274/4622946.html","https://www.booktxt.net/1_10274/4623347.html","https://www.booktxt.net/1_10274/4624396.html","https://www.booktxt.net/1_10274/4624821.html","https://www.booktxt.net/1_10274/4626445.html","https://www.booktxt.net/1_10274/4626751.html","https://www.booktxt.net/1_10274/4626995.html","https://www.booktxt.net/1_10274/4627514.html","https://www.booktxt.net/1_10274/4627796.html","https://www.booktxt.net/1_10274/4629749.html","https://www.booktxt.net/1_10274/4630244.html","https://www.booktxt.net/1_10274/4630651.html","https://www.booktxt.net/1_10274/4631184.html","https://www.booktxt.net/1_10274/4631487.html","https://www.booktxt.net/1_10274/4631926.html","https://www.booktxt.net/1_10274/4632658.html","https://www.booktxt.net/1_10274/4632908.html","https://www.booktxt.net/1_10274/4633426.html","https://www.booktxt.net/1_10274/4633850.html","https://www.booktxt.net/1_10274/4636205.html","https://www.booktxt.net/1_10274/4636266.html","https://www.booktxt.net/1_10274/4636268.html","https://www.booktxt.net/1_10274/4636270.html","https://www.booktxt.net/1_10274/4636437.html","https://www.booktxt.net/1_10274/4646991.html","https://www.booktxt.net/1_10274/4647199.html","https://www.booktxt.net/1_10274/4647200.html","https://www.booktxt.net/1_10274/4647201.html","https://www.booktxt.net/1_10274/4647430.html","https://www.booktxt.net/1_10274/4650756.html","https://www.booktxt.net/1_10274/4650974.html","https://www.booktxt.net/1_10274/4651193.html","https://www.booktxt.net/1_10274/4651281.html","https://www.booktxt.net/1_10274/4651538.html","https://www.booktxt.net/1_10274/4653406.html","https://www.booktxt.net/1_10274/4655448.html","https://www.booktxt.net/1_10274/4656305.html","https://www.booktxt.net/1_10274/4656565.html","https://www.booktxt.net/1_10274/4657250.html","https://www.booktxt.net/1_10274/4659297.html","https://www.booktxt.net/1_10274/4659775.html","https://www.booktxt.net/1_10274/4660275.html","https://www.booktxt.net/1_10274/4660760.html","https://www.booktxt.net/1_10274/4660820.html","https://www.booktxt.net/1_10274/4664313.html","https://www.booktxt.net/1_10274/4664603.html","https://www.booktxt.net/1_10274/4665029.html","https://www.booktxt.net/1_10274/4665288.html","https://www.booktxt.net/1_10274/4665924.html","https://www.booktxt.net/1_10274/4667970.html","https://www.booktxt.net/1_10274/4668436.html","https://www.booktxt.net/1_10274/4668593.html","https://www.booktxt.net/1_10274/4668910.html","https://www.booktxt.net/1_10274/4669379.html","https://www.booktxt.net/1_10274/4670253.html","https://www.booktxt.net/1_10274/4670307.html","https://www.booktxt.net/1_10274/4670458.html","https://www.booktxt.net/1_10274/4670615.html","https://www.booktxt.net/1_10274/4671256.html","https://www.booktxt.net/1_10274/4671628.html","https://www.booktxt.net/1_10274/4672046.html","https://www.booktxt.net/1_10274/4672324.html","https://www.booktxt.net/1_10274/4673297.html","https://www.booktxt.net/1_10274/4673387.html","https://www.booktxt.net/1_10274/4673746.html","https://www.booktxt.net/1_10274/4674083.html","https://www.booktxt.net/1_10274/4674425.html","https://www.booktxt.net/1_10274/4675198.html","https://www.booktxt.net/1_10274/4675771.html","https://www.booktxt.net/1_10274/4677905.html","https://www.booktxt.net/1_10274/4681260.html","https://www.booktxt.net/1_10274/4681492.html","https://www.booktxt.net/1_10274/4687181.html","https://www.booktxt.net/1_10274/4690322.html","https://www.booktxt.net/1_10274/4691981.html","https://www.booktxt.net/1_10274/4692640.html","https://www.booktxt.net/1_10274/4693207.html","https://www.booktxt.net/1_10274/4694931.html","https://www.booktxt.net/1_10274/4696813.html","https://www.booktxt.net/1_10274/4698183.html","https://www.booktxt.net/1_10274/4698267.html","https://www.booktxt.net/1_10274/4698607.html","https://www.booktxt.net/1_10274/4698989.html","https://www.booktxt.net/1_10274/4699152.html","https://www.booktxt.net/1_10274/4699467.html","https://www.booktxt.net/1_10274/4700182.html","https://www.booktxt.net/1_10274/4701733.html","https://www.booktxt.net/1_10274/4701734.html","https://www.booktxt.net/1_10274/4702515.html","https://www.booktxt.net/1_10274/4702516.html","https://www.booktxt.net/1_10274/4702685.html","https://www.booktxt.net/1_10274/4702931.html","https://www.booktxt.net/1_10274/4703658.html","https://www.booktxt.net/1_10274/4703719.html","https://www.booktxt.net/1_10274/4704680.html","https://www.booktxt.net/1_10274/4705163.html","https://www.booktxt.net/1_10274/4705591.html","https://www.booktxt.net/1_10274/4705592.html","https://www.booktxt.net/1_10274/4705918.html","https://www.booktxt.net/1_10274/4706648.html","https://www.booktxt.net/1_10274/4706649.html","https://www.booktxt.net/1_10274/4706953.html","https://www.booktxt.net/1_10274/4708349.html","https://www.booktxt.net/1_10274/4708398.html","https://www.booktxt.net/1_10274/4708532.html","https://www.booktxt.net/1_10274/4708800.html","https://www.booktxt.net/1_10274/4709598.html","https://www.booktxt.net/1_10274/4709712.html","https://www.booktxt.net/1_10274/4710137.html","https://www.booktxt.net/1_10274/4711511.html","https://www.booktxt.net/1_10274/4711828.html","https://www.booktxt.net/1_10274/4712569.html","https://www.booktxt.net/1_10274/4714630.html","https://www.booktxt.net/1_10274/4714928.html","https://www.booktxt.net/1_10274/4715988.html","https://www.booktxt.net/1_10274/4717576.html","https://www.booktxt.net/1_10274/4718378.html","https://www.booktxt.net/1_10274/4720454.html","https://www.booktxt.net/1_10274/4732622.html","https://www.booktxt.net/1_10274/4732623.html","https://www.booktxt.net/1_10274/4732624.html","https://www.booktxt.net/1_10274/4734139.html","https://www.booktxt.net/1_10274/4734140.html","https://www.booktxt.net/1_10274/4742363.html","https://www.booktxt.net/1_10274/4742907.html","https://www.booktxt.net/1_10274/4742908.html","https://www.booktxt.net/1_10274/4743646.html","https://www.booktxt.net/1_10274/4745096.html","https://www.booktxt.net/1_10274/4745372.html","https://www.booktxt.net/1_10274/4745820.html","https://www.booktxt.net/1_10274/4746538.html","https://www.booktxt.net/1_10274/4758125.html","https://www.booktxt.net/1_10274/4759269.html","https://www.booktxt.net/1_10274/4765411.html","https://www.booktxt.net/1_10274/4772383.html","https://www.booktxt.net/1_10274/4773732.html","https://www.booktxt.net/1_10274/4773733.html","https://www.booktxt.net/1_10274/4787625.html","https://www.booktxt.net/1_10274/4788137.html","https://www.booktxt.net/1_10274/4788864.html","https://www.booktxt.net/1_10274/4792217.html","https://www.booktxt.net/1_10274/4794199.html","https://www.booktxt.net/1_10274/4800608.html","https://www.booktxt.net/1_10274/4800609.html","https://www.booktxt.net/1_10274/4800610.html","https://www.booktxt.net/1_10274/4800611.html","https://www.booktxt.net/1_10274/4800612.html","https://www.booktxt.net/1_10274/4800613.html","https://www.booktxt.net/1_10274/4801225.html","https://www.booktxt.net/1_10274/4806964.html","https://www.booktxt.net/1_10274/4807958.html","https://www.booktxt.net/1_10274/4807959.html","https://www.booktxt.net/1_10274/4810690.html","https://www.booktxt.net/1_10274/4811765.html","https://www.booktxt.net/1_10274/4813171.html","https://www.booktxt.net/1_10274/4825408.html","https://www.booktxt.net/1_10274/4826420.html","https://www.booktxt.net/1_10274/4830507.html","https://www.booktxt.net/1_10274/4840243.html","https://www.booktxt.net/1_10274/4840244.html","https://www.booktxt.net/1_10274/4841252.html","https://www.booktxt.net/1_10274/4845745.html","https://www.booktxt.net/1_10274/4846239.html","https://www.booktxt.net/1_10274/4849370.html","https://www.booktxt.net/1_10274/4854258.html","https://www.booktxt.net/1_10274/4854259.html","https://www.booktxt.net/1_10274/4859338.html","https://www.booktxt.net/1_10274/4859339.html","https://www.booktxt.net/1_10274/4863304.html","https://www.booktxt.net/1_10274/4863305.html","https://www.booktxt.net/1_10274/4865703.html","https://www.booktxt.net/1_10274/4870630.html","https://www.booktxt.net/1_10274/4871395.html","https://www.booktxt.net/1_10274/4874740.html","https://www.booktxt.net/1_10274/4875170.html","https://www.booktxt.net/1_10274/4877429.html","https://www.booktxt.net/1_10274/4879138.html","https://www.booktxt.net/1_10274/4890426.html","https://www.booktxt.net/1_10274/4890427.html","https://www.booktxt.net/1_10274/4890428.html","https://www.booktxt.net/1_10274/4890429.html","https://www.booktxt.net/1_10274/4891216.html","https://www.booktxt.net/1_10274/4892359.html","https://www.booktxt.net/1_10274/4895665.html","https://www.booktxt.net/1_10274/4896611.html","https://www.booktxt.net/1_10274/4896612.html","https://www.booktxt.net/1_10274/4898762.html","https://www.booktxt.net/1_10274/4901069.html","https://www.booktxt.net/1_10274/4901630.html","https://www.booktxt.net/1_10274/4901949.html","https://www.booktxt.net/1_10274/4903824.html","https://www.booktxt.net/1_10274/4906823.html","https://www.booktxt.net/1_10274/4907911.html","https://www.booktxt.net/1_10274/4909336.html","https://www.booktxt.net/1_10274/4913508.html","https://www.booktxt.net/1_10274/4919593.html","https://www.booktxt.net/1_10274/4920589.html","https://www.booktxt.net/1_10274/4922992.html","https://www.booktxt.net/1_10274/4922993.html","https://www.booktxt.net/1_10274/4923535.html","https://www.booktxt.net/1_10274/4926003.html","https://www.booktxt.net/1_10274/4926499.html","https://www.booktxt.net/1_10274/4929307.html","https://www.booktxt.net/1_10274/4932028.html","https://www.booktxt.net/1_10274/4932029.html","https://www.booktxt.net/1_10274/4932591.html","https://www.booktxt.net/1_10274/4933896.html","https://www.booktxt.net/1_10274/4937112.html","https://www.booktxt.net/1_10274/4937113.html","https://www.booktxt.net/1_10274/4939628.html","https://www.booktxt.net/1_10274/4940130.html","https://www.booktxt.net/1_10274/4942488.html","https://www.booktxt.net/1_10274/4942910.html","https://www.booktxt.net/1_10274/4943532.html","https://www.booktxt.net/1_10274/4949573.html","https://www.booktxt.net/1_10274/4949574.html","https://www.booktxt.net/1_10274/4949575.html","https://www.booktxt.net/1_10274/4949576.html","https://www.booktxt.net/1_10274/4951070.html","https://www.booktxt.net/1_10274/4954239.html","https://www.booktxt.net/1_10274/4959418.html","https://www.booktxt.net/1_10274/4964310.html","https://www.booktxt.net/1_10274/4966171.html","https://www.booktxt.net/1_10274/4972728.html","https://www.booktxt.net/1_10274/4973324.html","https://www.booktxt.net/1_10274/4977320.html","https://www.booktxt.net/1_10274/4977953.html","https://www.booktxt.net/1_10274/4979040.html","https://www.booktxt.net/1_10274/4980977.html","https://www.booktxt.net/1_10274/4982130.html","https://www.booktxt.net/1_10274/4982733.html","https://www.booktxt.net/1_10274/4984581.html","https://www.booktxt.net/1_10274/4984868.html","https://www.booktxt.net/1_10274/4985057.html","https://www.booktxt.net/1_10274/4985402.html","https://www.booktxt.net/1_10274/4989563.html","https://www.booktxt.net/1_10274/4989882.html","https://www.booktxt.net/1_10274/5026284.html","https://www.booktxt.net/1_10274/5026285.html","https://www.booktxt.net/1_10274/5026286.html","https://www.booktxt.net/1_10274/5026287.html","https://www.booktxt.net/1_10274/5026288.html","https://www.booktxt.net/1_10274/5026289.html","https://www.booktxt.net/1_10274/5026290.html","https://www.booktxt.net/1_10274/5026291.html","https://www.booktxt.net/1_10274/5026292.html","https://www.booktxt.net/1_10274/5026293.html","https://www.booktxt.net/1_10274/5026294.html","https://www.booktxt.net/1_10274/5026295.html","https://www.booktxt.net/1_10274/5026296.html","https://www.booktxt.net/1_10274/5026297.html","https://www.booktxt.net/1_10274/5026298.html","https://www.booktxt.net/1_10274/5026299.html","https://www.booktxt.net/1_10274/5026300.html","https://www.booktxt.net/1_10274/5026301.html","https://www.booktxt.net/1_10274/5026302.html","https://www.booktxt.net/1_10274/5026303.html","https://www.booktxt.net/1_10274/5028284.html","https://www.booktxt.net/1_10274/5030849.html","https://www.booktxt.net/1_10274/5044072.html","https://www.booktxt.net/1_10274/5044073.html","https://www.booktxt.net/1_10274/5044074.html","https://www.booktxt.net/1_10274/5044075.html","https://www.booktxt.net/1_10274/5044076.html","https://www.booktxt.net/1_10274/5063153.html","https://www.booktxt.net/1_10274/5063154.html","https://www.booktxt.net/1_10274/5064055.html","https://www.booktxt.net/1_10274/5065737.html","https://www.booktxt.net/1_10274/5067509.html","https://www.booktxt.net/1_10274/5075217.html","https://www.booktxt.net/1_10274/5076142.html","https://www.booktxt.net/1_10274/5085855.html","https://www.booktxt.net/1_10274/5086455.html","https://www.booktxt.net/1_10274/5091168.html","https://www.booktxt.net/1_10274/5091169.html","https://www.booktxt.net/1_10274/5093719.html","https://www.booktxt.net/1_10274/5093720.html","https://www.booktxt.net/1_10274/5096253.html","https://www.booktxt.net/1_10274/5097609.html","https://www.booktxt.net/1_10274/5098471.html","https://www.booktxt.net/1_10274/5098472.html","https://www.booktxt.net/1_10274/5107488.html","https://www.booktxt.net/1_10274/5107489.html","https://www.booktxt.net/1_10274/5107490.html","https://www.booktxt.net/1_10274/5113424.html","https://www.booktxt.net/1_10274/5113598.html","https://www.booktxt.net/1_10274/5118149.html","https://www.booktxt.net/1_10274/5120112.html","https://www.booktxt.net/1_10274/5138739.html","https://www.booktxt.net/1_10274/5139347.html","https://www.booktxt.net/1_10274/5149568.html","https://www.booktxt.net/1_10274/5149569.html","https://www.booktxt.net/1_10274/5178230.html","https://www.booktxt.net/1_10274/5178231.html","https://www.booktxt.net/1_10274/5178232.html","https://www.booktxt.net/1_10274/5178233.html","https://www.booktxt.net/1_10274/5178234.html","https://www.booktxt.net/1_10274/5178235.html","https://www.booktxt.net/1_10274/5178236.html","https://www.booktxt.net/1_10274/5179913.html","https://www.booktxt.net/1_10274/5186567.html","https://www.booktxt.net/1_10274/5187351.html","https://www.booktxt.net/1_10274/5190590.html","https://www.booktxt.net/1_10274/5191159.html","https://www.booktxt.net/1_10274/5196292.html","https://www.booktxt.net/1_10274/5202257.html","https://www.booktxt.net/1_10274/5202258.html","https://www.booktxt.net/1_10274/5204857.html","https://www.booktxt.net/1_10274/5204862.html","https://www.booktxt.net/1_10274/5209216.html","https://www.booktxt.net/1_10274/5209243.html","https://www.booktxt.net/1_10274/5211455.html","https://www.booktxt.net/1_10274/5211655.html","https://www.booktxt.net/1_10274/5214978.html","https://www.booktxt.net/1_10274/5219375.html","https://www.booktxt.net/1_10274/5219376.html","https://www.booktxt.net/1_10274/5220364.html","https://www.booktxt.net/1_10274/5224355.html","https://www.booktxt.net/1_10274/5224663.html","https://www.booktxt.net/1_10274/5226828.html","https://www.booktxt.net/1_10274/5227076.html","https://www.booktxt.net/1_10274/5227420.html","https://www.booktxt.net/1_10274/5228081.html","https://www.booktxt.net/1_10274/5228880.html","https://www.booktxt.net/1_10274/5231214.html","https://www.booktxt.net/1_10274/5231443.html","https://www.booktxt.net/1_10274/5232003.html","https://www.booktxt.net/1_10274/5232497.html","https://www.booktxt.net/1_10274/5232498.html","https://www.booktxt.net/1_10274/5234705.html","https://www.booktxt.net/1_10274/5236445.html","https://www.booktxt.net/1_10274/5236446.html","https://www.booktxt.net/1_10274/5240208.html","https://www.booktxt.net/1_10274/5240209.html","https://www.booktxt.net/1_10274/5240210.html","https://www.booktxt.net/1_10274/5242688.html","https://www.booktxt.net/1_10274/5243046.html","https://www.booktxt.net/1_10274/5243578.html","https://www.booktxt.net/1_10274/5244771.html","https://www.booktxt.net/1_10274/5246739.html","https://www.booktxt.net/1_10274/5247567.html","https://www.booktxt.net/1_10274/5252163.html","https://www.booktxt.net/1_10274/5252164.html","https://www.booktxt.net/1_10274/5252165.html","https://www.booktxt.net/1_10274/5254145.html","https://www.booktxt.net/1_10274/5254146.html","https://www.booktxt.net/1_10274/5264050.html","https://www.booktxt.net/1_10274/5264051.html","https://www.booktxt.net/1_10274/5264052.html","https://www.booktxt.net/1_10274/5264053.html","https://www.booktxt.net/1_10274/5264054.html","https://www.booktxt.net/1_10274/5264055.html","https://www.booktxt.net/1_10274/5264056.html","https://www.booktxt.net/1_10274/5264639.html","https://www.booktxt.net/1_10274/5266168.html","https://www.booktxt.net/1_10274/5269858.html","https://www.booktxt.net/1_10274/5270250.html","https://www.booktxt.net/1_10274/5273713.html","https://www.booktxt.net/1_10274/5273714.html","https://www.booktxt.net/1_10274/5276839.html","https://www.booktxt.net/1_10274/5276841.html","https://www.booktxt.net/1_10274/5277350.html","https://www.booktxt.net/1_10274/5282183.html","https://www.booktxt.net/1_10274/5307982.html","https://www.booktxt.net/1_10274/5317062.html","https://www.booktxt.net/1_10274/5317063.html","https://www.booktxt.net/1_10274/5320020.html","https://www.booktxt.net/1_10274/5320987.html","https://www.booktxt.net/1_10274/5327800.html","https://www.booktxt.net/1_10274/5329813.html","https://www.booktxt.net/1_10274/5329836.html","https://www.booktxt.net/1_10274/5332457.html","https://www.booktxt.net/1_10274/5333289.html","https://www.booktxt.net/1_10274/5338932.html","https://www.booktxt.net/1_10274/5347568.html","https://www.booktxt.net/1_10274/5347569.html","https://www.booktxt.net/1_10274/5349599.html","https://www.booktxt.net/1_10274/5351377.html","https://www.booktxt.net/1_10274/5352860.html","https://www.booktxt.net/1_10274/5354064.html","https://www.booktxt.net/1_10274/5359985.html","https://www.booktxt.net/1_10274/5359986.html","https://www.booktxt.net/1_10274/5366328.html","https://www.booktxt.net/1_10274/5367378.html","https://www.booktxt.net/1_10274/5374383.html","https://www.booktxt.net/1_10274/5375215.html","https://www.booktxt.net/1_10274/5378059.html","https://www.booktxt.net/1_10274/5379398.html","https://www.booktxt.net/1_10274/5388580.html","https://www.booktxt.net/1_10274/5389961.html","https://www.booktxt.net/1_10274/5392868.html","https://www.booktxt.net/1_10274/5394342.html","https://www.booktxt.net/1_10274/5396885.html","https://www.booktxt.net/1_10274/5398023.html","https://www.booktxt.net/1_10274/5401756.html","https://www.booktxt.net/1_10274/5401757.html","https://www.booktxt.net/1_10274/5403018.html","https://www.booktxt.net/1_10274/5403019.html","https://www.booktxt.net/1_10274/5403309.html","https://www.booktxt.net/1_10274/5413342.html","https://www.booktxt.net/1_10274/5413343.html","https://www.booktxt.net/1_10274/5413344.html","https://www.booktxt.net/1_10274/5413345.html","https://www.booktxt.net/1_10274/5413346.html","https://www.booktxt.net/1_10274/5413347.html","https://www.booktxt.net/1_10274/5413348.html","https://www.booktxt.net/1_10274/5413349.html","https://www.booktxt.net/1_10274/5413350.html","https://www.booktxt.net/1_10274/5416818.html","https://www.booktxt.net/1_10274/5417441.html","https://www.booktxt.net/1_10274/5418246.html"],"graspTimeDifference":4406,"lastUpdateTime":"03-16","index":10274,"timeStamp":1556112259814}