{"name":"哈利波特之银河帝国","targetUrl":"https://www.booktxt.net/1_11556","author":"素手织梦","downloadUrl":"/modules/article/txtarticle.php?id=11556","allChapterNumber":139,"chapterList":["https://www.booktxt.net/1_11556/5127655.html","https://www.booktxt.net/1_11556/5137101.html","https://www.booktxt.net/1_11556/5137103.html","https://www.booktxt.net/1_11556/5137105.html","https://www.booktxt.net/1_11556/5137107.html","https://www.booktxt.net/1_11556/5137109.html","https://www.booktxt.net/1_11556/5137111.html","https://www.booktxt.net/1_11556/5137113.html","https://www.booktxt.net/1_11556/5137115.html","https://www.booktxt.net/1_11556/5137117.html","https://www.booktxt.net/1_11556/5137120.html","https://www.booktxt.net/1_11556/5137122.html","https://www.booktxt.net/1_11556/5137124.html","https://www.booktxt.net/1_11556/5137126.html","https://www.booktxt.net/1_11556/5137128.html","https://www.booktxt.net/1_11556/5137130.html","https://www.booktxt.net/1_11556/5137132.html","https://www.booktxt.net/1_11556/5137134.html","https://www.booktxt.net/1_11556/5137136.html","https://www.booktxt.net/1_11556/5137138.html","https://www.booktxt.net/1_11556/5137140.html","https://www.booktxt.net/1_11556/5137142.html","https://www.booktxt.net/1_11556/5137144.html","https://www.booktxt.net/1_11556/5137146.html","https://www.booktxt.net/1_11556/5137148.html","https://www.booktxt.net/1_11556/5137150.html","https://www.booktxt.net/1_11556/5137152.html","https://www.booktxt.net/1_11556/5137154.html","https://www.booktxt.net/1_11556/5137156.html","https://www.booktxt.net/1_11556/5137158.html","https://www.booktxt.net/1_11556/5137160.html","https://www.booktxt.net/1_11556/5137162.html","https://www.booktxt.net/1_11556/5137164.html","https://www.booktxt.net/1_11556/5137166.html","https://www.booktxt.net/1_11556/5137168.html","https://www.booktxt.net/1_11556/5137170.html","https://www.booktxt.net/1_11556/5137172.html","https://www.booktxt.net/1_11556/5137174.html","https://www.booktxt.net/1_11556/5137176.html","https://www.booktxt.net/1_11556/5137178.html","https://www.booktxt.net/1_11556/5137180.html","https://www.booktxt.net/1_11556/5137182.html","https://www.booktxt.net/1_11556/5137184.html","https://www.booktxt.net/1_11556/5137186.html","https://www.booktxt.net/1_11556/5137188.html","https://www.booktxt.net/1_11556/5137190.html","https://www.booktxt.net/1_11556/5137192.html","https://www.booktxt.net/1_11556/5137193.html","https://www.booktxt.net/1_11556/5137195.html","https://www.booktxt.net/1_11556/5137196.html","https://www.booktxt.net/1_11556/5137197.html","https://www.booktxt.net/1_11556/5137199.html","https://www.booktxt.net/1_11556/5137200.html","https://www.booktxt.net/1_11556/5137202.html","https://www.booktxt.net/1_11556/5137203.html","https://www.booktxt.net/1_11556/5137204.html","https://www.booktxt.net/1_11556/5137205.html","https://www.booktxt.net/1_11556/5137207.html","https://www.booktxt.net/1_11556/5137208.html","https://www.booktxt.net/1_11556/5137209.html","https://www.booktxt.net/1_11556/5137211.html","https://www.booktxt.net/1_11556/5137212.html","https://www.booktxt.net/1_11556/5146342.html","https://www.booktxt.net/1_11556/5165431.html","https://www.booktxt.net/1_11556/5169853.html","https://www.booktxt.net/1_11556/5173060.html","https://www.booktxt.net/1_11556/5179445.html","https://www.booktxt.net/1_11556/5185604.html","https://www.booktxt.net/1_11556/5192196.html","https://www.booktxt.net/1_11556/5195153.html","https://www.booktxt.net/1_11556/5202172.html","https://www.booktxt.net/1_11556/5209373.html","https://www.booktxt.net/1_11556/5213617.html","https://www.booktxt.net/1_11556/5216817.html","https://www.booktxt.net/1_11556/5220484.html","https://www.booktxt.net/1_11556/5224694.html","https://www.booktxt.net/1_11556/5228408.html","https://www.booktxt.net/1_11556/5231553.html","https://www.booktxt.net/1_11556/5235736.html","https://www.booktxt.net/1_11556/5240693.html","https://www.booktxt.net/1_11556/5247805.html","https://www.booktxt.net/1_11556/5251600.html","https://www.booktxt.net/1_11556/5255213.html","https://www.booktxt.net/1_11556/5259794.html","https://www.booktxt.net/1_11556/5265124.html","https://www.booktxt.net/1_11556/5271145.html","https://www.booktxt.net/1_11556/5276697.html","https://www.booktxt.net/1_11556/5315859.html","https://www.booktxt.net/1_11556/5321674.html","https://www.booktxt.net/1_11556/5330931.html","https://www.booktxt.net/1_11556/5332293.html","https://www.booktxt.net/1_11556/5334903.html","https://www.booktxt.net/1_11556/5338926.html","https://www.booktxt.net/1_11556/5348217.html","https://www.booktxt.net/1_11556/5349260.html","https://www.booktxt.net/1_11556/5353969.html","https://www.booktxt.net/1_11556/5355080.html","https://www.booktxt.net/1_11556/5360089.html","https://www.booktxt.net/1_11556/5371903.html","https://www.booktxt.net/1_11556/5375384.html","https://www.booktxt.net/1_11556/5376864.html","https://www.booktxt.net/1_11556/5379785.html","https://www.booktxt.net/1_11556/5379787.html","https://www.booktxt.net/1_11556/5379789.html","https://www.booktxt.net/1_11556/5379790.html","https://www.booktxt.net/1_11556/5387031.html","https://www.booktxt.net/1_11556/5388687.html","https://www.booktxt.net/1_11556/5391315.html","https://www.booktxt.net/1_11556/5392564.html","https://www.booktxt.net/1_11556/5395562.html","https://www.booktxt.net/1_11556/5397225.html","https://www.booktxt.net/1_11556/5399826.html","https://www.booktxt.net/1_11556/5408430.html","https://www.booktxt.net/1_11556/5408433.html","https://www.booktxt.net/1_11556/5412213.html","https://www.booktxt.net/1_11556/5418781.html","https://www.booktxt.net/1_11556/5422999.html","https://www.booktxt.net/1_11556/5423002.html","https://www.booktxt.net/1_11556/5433139.html","https://www.booktxt.net/1_11556/5433140.html","https://www.booktxt.net/1_11556/5434550.html","https://www.booktxt.net/1_11556/5439207.html","https://www.booktxt.net/1_11556/5441180.html","https://www.booktxt.net/1_11556/5447988.html","https://www.booktxt.net/1_11556/5451174.html","https://www.booktxt.net/1_11556/5454529.html","https://www.booktxt.net/1_11556/5457930.html","https://www.booktxt.net/1_11556/5464667.html","https://www.booktxt.net/1_11556/5473355.html","https://www.booktxt.net/1_11556/5474109.html","https://www.booktxt.net/1_11556/5478080.html","https://www.booktxt.net/1_11556/5478081.html","https://www.booktxt.net/1_11556/5479515.html","https://www.booktxt.net/1_11556/5479516.html","https://www.booktxt.net/1_11556/5482902.html","https://www.booktxt.net/1_11556/5492748.html","https://www.booktxt.net/1_11556/5497084.html","https://www.booktxt.net/1_11556/5499874.html","https://www.booktxt.net/1_11556/5504701.html"],"graspTimeDifference":1642,"lastUpdateTime":"04-13","index":11556,"timeStamp":1556112611011}