{"name":"最后一个僵尸","targetUrl":"https://www.booktxt.net/1_11774","author":"唃厮罗","downloadUrl":"/modules/article/txtarticle.php?id=11774","allChapterNumber":265,"chapterList":["https://www.booktxt.net/1_11774/5154745.html","https://www.booktxt.net/1_11774/5158186.html","https://www.booktxt.net/1_11774/5158187.html","https://www.booktxt.net/1_11774/5158188.html","https://www.booktxt.net/1_11774/5158189.html","https://www.booktxt.net/1_11774/5158190.html","https://www.booktxt.net/1_11774/5158191.html","https://www.booktxt.net/1_11774/5158192.html","https://www.booktxt.net/1_11774/5158193.html","https://www.booktxt.net/1_11774/5158194.html","https://www.booktxt.net/1_11774/5158195.html","https://www.booktxt.net/1_11774/5158196.html","https://www.booktxt.net/1_11774/5158197.html","https://www.booktxt.net/1_11774/5158198.html","https://www.booktxt.net/1_11774/5158199.html","https://www.booktxt.net/1_11774/5158200.html","https://www.booktxt.net/1_11774/5158201.html","https://www.booktxt.net/1_11774/5158202.html","https://www.booktxt.net/1_11774/5158203.html","https://www.booktxt.net/1_11774/5158204.html","https://www.booktxt.net/1_11774/5158205.html","https://www.booktxt.net/1_11774/5158206.html","https://www.booktxt.net/1_11774/5158207.html","https://www.booktxt.net/1_11774/5158208.html","https://www.booktxt.net/1_11774/5158209.html","https://www.booktxt.net/1_11774/5158210.html","https://www.booktxt.net/1_11774/5158211.html","https://www.booktxt.net/1_11774/5158212.html","https://www.booktxt.net/1_11774/5158215.html","https://www.booktxt.net/1_11774/5158216.html","https://www.booktxt.net/1_11774/5158217.html","https://www.booktxt.net/1_11774/5158219.html","https://www.booktxt.net/1_11774/5158220.html","https://www.booktxt.net/1_11774/5158222.html","https://www.booktxt.net/1_11774/5158224.html","https://www.booktxt.net/1_11774/5158225.html","https://www.booktxt.net/1_11774/5158228.html","https://www.booktxt.net/1_11774/5158230.html","https://www.booktxt.net/1_11774/5158231.html","https://www.booktxt.net/1_11774/5158232.html","https://www.booktxt.net/1_11774/5158233.html","https://www.booktxt.net/1_11774/5158234.html","https://www.booktxt.net/1_11774/5158235.html","https://www.booktxt.net/1_11774/5158237.html","https://www.booktxt.net/1_11774/5158238.html","https://www.booktxt.net/1_11774/5158239.html","https://www.booktxt.net/1_11774/5158240.html","https://www.booktxt.net/1_11774/5158241.html","https://www.booktxt.net/1_11774/5158242.html","https://www.booktxt.net/1_11774/5158243.html","https://www.booktxt.net/1_11774/5158244.html","https://www.booktxt.net/1_11774/5158245.html","https://www.booktxt.net/1_11774/5158246.html","https://www.booktxt.net/1_11774/5158247.html","https://www.booktxt.net/1_11774/5158248.html","https://www.booktxt.net/1_11774/5158250.html","https://www.booktxt.net/1_11774/5158251.html","https://www.booktxt.net/1_11774/5158252.html","https://www.booktxt.net/1_11774/5158253.html","https://www.booktxt.net/1_11774/5158254.html","https://www.booktxt.net/1_11774/5158255.html","https://www.booktxt.net/1_11774/5158256.html","https://www.booktxt.net/1_11774/5158257.html","https://www.booktxt.net/1_11774/5158258.html","https://www.booktxt.net/1_11774/5158259.html","https://www.booktxt.net/1_11774/5158260.html","https://www.booktxt.net/1_11774/5158261.html","https://www.booktxt.net/1_11774/5158262.html","https://www.booktxt.net/1_11774/5158263.html","https://www.booktxt.net/1_11774/5158264.html","https://www.booktxt.net/1_11774/5158265.html","https://www.booktxt.net/1_11774/5158266.html","https://www.booktxt.net/1_11774/5158268.html","https://www.booktxt.net/1_11774/5158269.html","https://www.booktxt.net/1_11774/5158271.html","https://www.booktxt.net/1_11774/5158272.html","https://www.booktxt.net/1_11774/5158273.html","https://www.booktxt.net/1_11774/5158274.html","https://www.booktxt.net/1_11774/5158275.html","https://www.booktxt.net/1_11774/5158276.html","https://www.booktxt.net/1_11774/5158277.html","https://www.booktxt.net/1_11774/5158278.html","https://www.booktxt.net/1_11774/5158279.html","https://www.booktxt.net/1_11774/5158280.html","https://www.booktxt.net/1_11774/5158281.html","https://www.booktxt.net/1_11774/5158282.html","https://www.booktxt.net/1_11774/5158284.html","https://www.booktxt.net/1_11774/5158285.html","https://www.booktxt.net/1_11774/5158286.html","https://www.booktxt.net/1_11774/5158287.html","https://www.booktxt.net/1_11774/5158289.html","https://www.booktxt.net/1_11774/5158290.html","https://www.booktxt.net/1_11774/5158291.html","https://www.booktxt.net/1_11774/5158292.html","https://www.booktxt.net/1_11774/5158294.html","https://www.booktxt.net/1_11774/5158295.html","https://www.booktxt.net/1_11774/5158296.html","https://www.booktxt.net/1_11774/5158297.html","https://www.booktxt.net/1_11774/5158298.html","https://www.booktxt.net/1_11774/5158300.html","https://www.booktxt.net/1_11774/5158301.html","https://www.booktxt.net/1_11774/5158302.html","https://www.booktxt.net/1_11774/5158303.html","https://www.booktxt.net/1_11774/5158304.html","https://www.booktxt.net/1_11774/5158305.html","https://www.booktxt.net/1_11774/5158307.html","https://www.booktxt.net/1_11774/5158309.html","https://www.booktxt.net/1_11774/5158310.html","https://www.booktxt.net/1_11774/5158311.html","https://www.booktxt.net/1_11774/5158313.html","https://www.booktxt.net/1_11774/5158314.html","https://www.booktxt.net/1_11774/5158315.html","https://www.booktxt.net/1_11774/5158316.html","https://www.booktxt.net/1_11774/5158317.html","https://www.booktxt.net/1_11774/5158318.html","https://www.booktxt.net/1_11774/5158319.html","https://www.booktxt.net/1_11774/5158320.html","https://www.booktxt.net/1_11774/5158321.html","https://www.booktxt.net/1_11774/5158322.html","https://www.booktxt.net/1_11774/5158323.html","https://www.booktxt.net/1_11774/5158325.html","https://www.booktxt.net/1_11774/5158326.html","https://www.booktxt.net/1_11774/5158327.html","https://www.booktxt.net/1_11774/5158331.html","https://www.booktxt.net/1_11774/5158332.html","https://www.booktxt.net/1_11774/5158333.html","https://www.booktxt.net/1_11774/5158335.html","https://www.booktxt.net/1_11774/5158336.html","https://www.booktxt.net/1_11774/5158337.html","https://www.booktxt.net/1_11774/5158338.html","https://www.booktxt.net/1_11774/5158339.html","https://www.booktxt.net/1_11774/5158340.html","https://www.booktxt.net/1_11774/5158341.html","https://www.booktxt.net/1_11774/5158342.html","https://www.booktxt.net/1_11774/5158343.html","https://www.booktxt.net/1_11774/5158345.html","https://www.booktxt.net/1_11774/5158347.html","https://www.booktxt.net/1_11774/5158349.html","https://www.booktxt.net/1_11774/5158350.html","https://www.booktxt.net/1_11774/5158353.html","https://www.booktxt.net/1_11774/5158355.html","https://www.booktxt.net/1_11774/5158356.html","https://www.booktxt.net/1_11774/5162962.html","https://www.booktxt.net/1_11774/5165299.html","https://www.booktxt.net/1_11774/5169313.html","https://www.booktxt.net/1_11774/5171772.html","https://www.booktxt.net/1_11774/5172897.html","https://www.booktxt.net/1_11774/5175778.html","https://www.booktxt.net/1_11774/5178004.html","https://www.booktxt.net/1_11774/5183049.html","https://www.booktxt.net/1_11774/5185498.html","https://www.booktxt.net/1_11774/5188932.html","https://www.booktxt.net/1_11774/5189258.html","https://www.booktxt.net/1_11774/5193095.html","https://www.booktxt.net/1_11774/5194822.html","https://www.booktxt.net/1_11774/5199750.html","https://www.booktxt.net/1_11774/5201604.html","https://www.booktxt.net/1_11774/5204436.html","https://www.booktxt.net/1_11774/5205257.html","https://www.booktxt.net/1_11774/5207789.html","https://www.booktxt.net/1_11774/5208623.html","https://www.booktxt.net/1_11774/5211342.html","https://www.booktxt.net/1_11774/5211759.html","https://www.booktxt.net/1_11774/5214581.html","https://www.booktxt.net/1_11774/5215276.html","https://www.booktxt.net/1_11774/5218014.html","https://www.booktxt.net/1_11774/5219165.html","https://www.booktxt.net/1_11774/5221832.html","https://www.booktxt.net/1_11774/5222726.html","https://www.booktxt.net/1_11774/5226308.html","https://www.booktxt.net/1_11774/5227359.html","https://www.booktxt.net/1_11774/5230843.html","https://www.booktxt.net/1_11774/5231514.html","https://www.booktxt.net/1_11774/5234426.html","https://www.booktxt.net/1_11774/5235070.html","https://www.booktxt.net/1_11774/5238485.html","https://www.booktxt.net/1_11774/5239066.html","https://www.booktxt.net/1_11774/5241445.html","https://www.booktxt.net/1_11774/5242849.html","https://www.booktxt.net/1_11774/5246396.html","https://www.booktxt.net/1_11774/5246628.html","https://www.booktxt.net/1_11774/5249064.html","https://www.booktxt.net/1_11774/5250149.html","https://www.booktxt.net/1_11774/5252713.html","https://www.booktxt.net/1_11774/5253715.html","https://www.booktxt.net/1_11774/5255987.html","https://www.booktxt.net/1_11774/5257103.html","https://www.booktxt.net/1_11774/5259442.html","https://www.booktxt.net/1_11774/5260275.html","https://www.booktxt.net/1_11774/5263245.html","https://www.booktxt.net/1_11774/5264189.html","https://www.booktxt.net/1_11774/5268046.html","https://www.booktxt.net/1_11774/5269403.html","https://www.booktxt.net/1_11774/5271844.html","https://www.booktxt.net/1_11774/5273132.html","https://www.booktxt.net/1_11774/5275917.html","https://www.booktxt.net/1_11774/5276965.html","https://www.booktxt.net/1_11774/5299778.html","https://www.booktxt.net/1_11774/5319687.html","https://www.booktxt.net/1_11774/5319688.html","https://www.booktxt.net/1_11774/5319689.html","https://www.booktxt.net/1_11774/5449202.html","https://www.booktxt.net/1_11774/5449203.html","https://www.booktxt.net/1_11774/5449205.html","https://www.booktxt.net/1_11774/5449207.html","https://www.booktxt.net/1_11774/5449208.html","https://www.booktxt.net/1_11774/5449209.html","https://www.booktxt.net/1_11774/5449210.html","https://www.booktxt.net/1_11774/5449211.html","https://www.booktxt.net/1_11774/5449212.html","https://www.booktxt.net/1_11774/5449214.html","https://www.booktxt.net/1_11774/5449215.html","https://www.booktxt.net/1_11774/5449216.html","https://www.booktxt.net/1_11774/5449217.html","https://www.booktxt.net/1_11774/5449218.html","https://www.booktxt.net/1_11774/5449219.html","https://www.booktxt.net/1_11774/5449220.html","https://www.booktxt.net/1_11774/5449221.html","https://www.booktxt.net/1_11774/5449222.html","https://www.booktxt.net/1_11774/5449223.html","https://www.booktxt.net/1_11774/5449224.html","https://www.booktxt.net/1_11774/5449225.html","https://www.booktxt.net/1_11774/5449226.html","https://www.booktxt.net/1_11774/5449227.html","https://www.booktxt.net/1_11774/5449228.html","https://www.booktxt.net/1_11774/5449229.html","https://www.booktxt.net/1_11774/5449230.html","https://www.booktxt.net/1_11774/5449231.html","https://www.booktxt.net/1_11774/5449232.html","https://www.booktxt.net/1_11774/5449233.html","https://www.booktxt.net/1_11774/5449234.html","https://www.booktxt.net/1_11774/5449235.html","https://www.booktxt.net/1_11774/5449236.html","https://www.booktxt.net/1_11774/5449237.html","https://www.booktxt.net/1_11774/5449238.html","https://www.booktxt.net/1_11774/5449239.html","https://www.booktxt.net/1_11774/5449240.html","https://www.booktxt.net/1_11774/5449241.html","https://www.booktxt.net/1_11774/5449242.html","https://www.booktxt.net/1_11774/5449243.html","https://www.booktxt.net/1_11774/5449245.html","https://www.booktxt.net/1_11774/5449246.html","https://www.booktxt.net/1_11774/5449247.html","https://www.booktxt.net/1_11774/5449248.html","https://www.booktxt.net/1_11774/5449249.html","https://www.booktxt.net/1_11774/5449250.html","https://www.booktxt.net/1_11774/5449251.html","https://www.booktxt.net/1_11774/5449253.html","https://www.booktxt.net/1_11774/5449254.html","https://www.booktxt.net/1_11774/5449255.html","https://www.booktxt.net/1_11774/5449256.html","https://www.booktxt.net/1_11774/5449257.html","https://www.booktxt.net/1_11774/5449258.html","https://www.booktxt.net/1_11774/5449259.html","https://www.booktxt.net/1_11774/5449261.html","https://www.booktxt.net/1_11774/5464720.html","https://www.booktxt.net/1_11774/5464721.html","https://www.booktxt.net/1_11774/5464722.html","https://www.booktxt.net/1_11774/5464723.html","https://www.booktxt.net/1_11774/5464724.html","https://www.booktxt.net/1_11774/5464725.html","https://www.booktxt.net/1_11774/5464726.html","https://www.booktxt.net/1_11774/5464727.html","https://www.booktxt.net/1_11774/5464728.html","https://www.booktxt.net/1_11774/5464729.html"],"graspTimeDifference":1985,"lastUpdateTime":"03-31","index":11774,"timeStamp":1556113028517}